Workbook

Sheet P&L
A1: KSB LTD
A3: Particular | B3: 2021 | C3: =B3+1 -> 2022 | D3: =C3+1 -> 2023 | E3: =D3+1 -> 2024 | F3: =E3+1 -> 2025
A4: Income
A5: Revenue from operations | B5: 14972.91 | C5: 18219.6 | D5: 22472.38 | E5: 25330.86 | F5: 26957
A6: Other income | B6: 336.94 | C6: 421.84 | D6: 323.37 | E6: 367.51 | F6: 592
A7: Total Income | B7: 15309.85 | C7: 18641.44 | D7: 22795.75 | E7: 25698.37 | F7: 27549
A8: Expenses
A9: Cost of materials consumed | B9: 7212.55 | C9: 8942.33 | D9: 10688.97 | E9: 12034.04 | F9: 12746
A10: Purchases of stock-in-trade | B10: 1353.31 | C10: 1687.73 | D10: 1907.05 | E10: 2567.34 | F10: 2749
A11: Changes in inventories of finished goods,
A12: work-in-progress and stock-in-trade | B12: -641.61 | C12: -750.05 | D12: 179.08 | E12: -379.94 | F12: -932
A13: Employee benefits expense | B13: 2153.75 | C13: 2438.97 | D13: 2696.83 | E13: 3135.19 | F13: 3643
A14: Finance costs | B14: 50.4 | C14: 61.26 | D14: 52.9 | E14: 27.17 | F14: 30
A15: Depreciation and amortisation expense | B15: 435.34 | C15: 452.61 | D15: 496.78 | E15: 543.24 | F15: 583
A16: Other expenses | B16: 2800.24 | C16: 3434.13 | D16: 4064.75 | E16: 4598.89 | F16: 5016
A17: Total Expenses | B17: 13363.98 | C17: 16266.98 | D17: 20086.36 | E17: 22525.93 | F17: =SUM(F9:F16) -> 23835
A18: Profit before share of net profit of associate accounted
A19: for using the equity method and tax | B19: 1945.87 | C19: 2374.46 | D19: 3172.44 | E19: 2709.39 | F19: 3714
A20: Share of net profit of associate accounted for using
A21: the equity method | B21: 64.2 | C21: 78.23 | D21: 94.1 | E21: 134.06 | F21: -255
A22: Profit before tax | B22: 2010.07 | C22: 2452.69 | D22: 2803.49 | E22: 3306.5 | F22: 3459
A23: Tax expense
A24: Current tax | B24: 560.5 | C24: 538.51 | D24: 721.62 | E24: 815.07 | F24: 1007
A25: Deferred tax | B25: -44.32 | C25: 86.77 | D25: -5.46 | E25: 16.68 | F25: -107
A26: Total tax expense | B26: 516.18 | C26: 625.28 | D26: 716.16 | E26: 831.75 | F26: 900
A27: Profit for the year | B27: 1493.89 | C27: 1827.41 | D27: 2087.33 | E27: 2474.75 | F27: 2559
A28: Other comprehensive income
A29: Items that will not be reclassified to profit or loss
A30: Remeasurement of post-employment benefit obligations | B30: 8.54 | C30: -90.56 | D30: -36.73 | E30: 31.73 | F30: 0
A31: Income tax relating to items that will not be reclassified to
A32: profit or loss | B32: -2.15 | C32: 22.79 | D32: -7.98 | E32: 9.25 | F32: 0
A33: Share of Other comprehensive income of associate
A34: accounted for using the equity method | B34: -2.21 | C34: -1.76 | D34: -1.03 | E34: -3.72 | F34: =146 -> 146
A35: Total other comprehensive income for the year, net of tax | B35: 4.18 | C35: -69.53 | D35: 22.72 | E35: -31.2 | F35: -75
A36: Total comprehensive income for the year | B36: 1498.07 | C36: 1757.88 | D36: 2110.05 | E36: 2443.55 | F36: 2630
A37: Earnings per equity share
A38: Basic and Diluted (face value of ` 2/- each)

Sheet Balance Sheet
A1: KSB LTD
C3: 2021 | D3: =C3+1 -> 2022 | E3: =D3+1 -> 2023 | F3: =E3+1 -> 2024 | G3: =F3+1 -> 2025
A4: ASSETS
A5: I. | B5: Non-current assets
B6: Property, plant and equipment | C6: 2819.53 | D6: 3214.64 | E6: 3710.4 | F6: 3864.74 | G6: 4084
B7: Right-of-use assets | C7: 273.43 | D7: 269.08 | E7: 269.25 | F7: 327.18 | G7: 0
B8: Capital work-in-progress | C8: 391.76 | D8: 251.43 | E8: 310.25 | F8: 528.08 | G8: 889
B9: Other Intangible assets | C9: 13.41 | D9: 17.05 | E9: 210.24 | F9: 192.72 | G9: 192
B10: Intangible assets under development | C10: 0 | D10: 0 | E10: 13.75 | F10: 18.48 | G10: 30
B11: Financial assets
B12: (a) Investments | C12: 697.48 | D12: 741.61 | E12: 795.36 | F12: 878.28 | G12: 965
B13: (b) Trade receivables | C13: 145.36 | D13: 98.24 | E13: 42.34 | F13: 19.14 | G13: 26
B14: (c) Loans | C14: 122.27 | D14: 91.19 | E14: 73.91 | F14: 80.24 | G14: 83
B15: (d) Other financial assets | C15: 51.1 | D15: 46.33 | E15: 42.28 | F15: 77.98 | G15: 63
B16: Deferred tax Current (net) | C16: 0 | D16: 0 | E16: 0 | F16: 0 | G16: 109
B17: Assets for current tax (net) | C17: 162.57 | D17: 210.77 | E17: 185.07 | F17: 112.17 | G17: 0
B18: Other non-current assets | C18: 214.59 | D18: 569.66 | E18: 343.23 | F18: 344.18 | G18: 736
B19: Total non-current assets | C19: 4891.5 | D19: 5510 | E19: 5996.08 | F19: 6443.19 | G19: 7177
A20: II. | B20: Current assets
B21: Inventories | C21: 4230.84 | D21: 5610.89 | E21: 6426.34 | F21: 6428.23 | G21: 7861
B23: (a) Trade receivables | C23: 2779.83 | D23: 4036.53 | E23: 4917.19 | F23: 6502.73 | G23: 8692
B24: (b) Cash and cash equivalents | C24: 565.65 | D24: 319.54 | E24: 1195.28 | F24: 959.01 | G24: 1668
B25: (c) Bank balances other than (b) above | C25: 2979.65 | D25: 2290.53 | E25: 1550.4 | F25: 2275.67 | G25: 1166
B26: (d) Loans | C26: 27.08 | D26: 39.34 | E26: 27.96 | F26: 52.95 | G26: 49
B27: (e) Other financial assets | C27: 101.24 | D27: 89.94 | E27: 114.75 | F27: 116.69 | G27: 200
B28: Other current assets | C28: 517.95 | D28: 351.35 | E28: 429.43 | F28: 701.81 | G28: 1113
B29: Total current assets | C29: 11202.24 | D29: 12738.12 | E29: 14661.35 | F29: 17037.09 | G29: 20749
B30: Total Assets | C30: 16093.74 | D30: 18248.12 | E30: 20657.43 | F30: 23480.28 | G30: 27926
A31: EQUITY AND LIABILITIES
B32: EQUITY
B33: Equity share capital | C33: 348.08 | D33: 348.08 | E33: 348.08 | F33: 348.08 | G33: 348.08
B34: Other equity | C34: 9760.3 | D34: 11083.08 | E34: 12671.01 | F34: 14505.42 | G34: 16439.92
B35: Total Equity | C35: 10108.38 | D35: 11431.16 | E35: 13019.09 | F35: 14853.5 | G35: 16788
B36: LIABILITIES
B37: I. Non-current liabilities
B38: Financial liabilities
B39: (a) Lease liabilities | C39: 20.34 | D39: 19.51 | E39: 21.02 | F39: 21.67 | G39: 42
B40: Provisions | C40: 516.67 | D40: 433.1 | E40: 437 | F40: 569.82 | G40: 851
B41: Deferred tax liabilities (net) | C41: 0 | D41: 12.88 | E41: 15.4 | F41: 22.83 | G41: 0
B42: Total non-current liabilities | C42: 537.01 | D42: 465.49 | E42: 473.42 | F42: 614.32 | G42: 893
B43: II. Current liabilities
B44: Financial liabilities
B45: (a) Lease liabilities | C45: 9.55 | D45: 9.31 | E45: 11.34 | F45: 12.69 | G45: 0
B46: (b) Trade payables
B47: Total outstanding dues of micro enterprises | C47: 212.05 | D47: 482.97 | E47: 473.09 | F47: 347.31 | G47: 492
B48: and small enterprises
B49: Total outstanding dues of creditors other than | C49: 2579.5 | D49: 2659.7 | E49: 2959.46 | F49: 3406.08 | G49: 3921
B50: micro enterprises and small enterprises
B51: (c) Other financial liabilities | C51: 827.15 | D51: 733.89 | E51: 925.02 | F51: 955.44 | G51: 712
B52: Other current liabilities | C52: 1261.71 | D52: 1962.66 | E52: 2258.52 | F52: 2657.72 | G52: 4242
B53: Provisions | C53: 540.75 | D53: 502.94 | E53: 537.49 | F53: 558.52 | G53: 839
B54: Current tax liabilities (net) | C54: 17.64 | D54: 0 | E54: 0 | F54: 74.7 | G54: 39
B55: Total current liabilities | C55: 5448.35 | D55: 6351.47 | E55: 7164.92 | F55: 8012.46 | G55: 10245
B56: Total Liabilities | C56: 5985.36 | D56: 6816.96 | E56: 7638.34 | F56: 8626.78 | G56: 11138
B57: Total Equity and Liabilities | C57: 16093.74 | D57: 18248.12 | E57: 20657.43 | F57: 23480.28 | G57: 27926

Sheet Scenario
A1: KSB LTD
A2: Scenario
B4: Scenario | C4: Growth(%) | F4: 2026 | G4: =F4+1 -> 2027 | H4: =G4+1 -> 2028 | I4: =H4+1 -> 2029 | J4: =I4+1 -> 2030
B5: Base Case | C5: 0.08 | F5: =C5 -> 0.08 | G5: =F5*(1-$C$8) -> 0.068 | H5: =G5*(1-$C$8) -> 0.0578 | I5: =H5*(1-$C$8) -> 0.04913 | J5: =I5*(1-$C$8) -> 0.0417605
B6: Bull Case | C6: =MAX(Model!I8:L8) -> 0.23341786 | F6: =C6 -> 0.23341786 | G6: =F6*(1-$C$8) -> 0.19840518 | H6: =G6*(1-$C$8) -> 0.1686444 | I6: =H6*(1-$C$8) -> 0.14334774 | J6: =I6*(1-$C$8) -> 0.12184558
B7: Bear Case | C7: =MIN(Model!I8:L8) -> 0.064196004 | F7: =C7 -> 0.064196004 | G7: =F7*(1-$C$8) -> 0.054566604 | H7: =G7*(1-$C$8) -> 0.046381613 | I7: =H7*(1-$C$8) -> 0.039424371 | J7: =I7*(1-$C$8) -> 0.033510716
B8: Annual Growth Tampering | C8: 0.15

Sheet C&F
A1: KSB LTD
C3: 2021 | D3: =C3+1 -> 2022 | E3: =D3+1 -> 2023 | F3: =E3+1 -> 2024 | G3: =F3+1 -> 2025
A5: A. | B5: Cash flow from operating activities
B6: Profit before tax | C6: 2010.07 | D6: 2452.69 | E6: 2803.49 | F6: 3306.5 | G6: 3459
B7: Adjustments for :
B8: Depreciation and amortisation expense | C8: 435.34 | D8: 452.61 | E8: 496.78 | F8: 543.24 | G8: 583
B9: Net (gain)/loss on disposal of property, | C9: 3.69 | D9: -13.49 | E9: -2.21 | F9: -6.32 | G9: 0
B10: plant and equipment
B11: Finance costs | C11: 50.4 | D11: 61.26 | E11: 52.9 | F11: 27.17 | G11: 30
B12: Interest income | C12: -195.76 | D12: -193.8 | E12: -163.27 | F12: -239.47 | G12: -199
B13: Fair value loss in derivative financial instruments | C13: 5.64 | D13: 3.14 | E13: -2.72 | F13: 1.4 | G13: -88
B14: Sundry credit balances and provisions
B15: no longer required, written back | C15: -3.77 | D15: -14.42 | E15: -3.45 | F15: 0 | G15: -1
B16: Unrealised foreign exchange gain | C16: -11.91 | D16: -18.93 | E16: 8.61 | F16: 4.78 | G16: 0
B17: Allowance for doubtful receivables | C17: 30.86 | D17: -41.64 | E17: -55.49 | F17: 71.89 | G17: 0
B18: Share of net profit of associates | C18: -64.2 | D18: -78.23 | E18: -94.1 | F18: -134.06 | G18: -105
C19: =SUM(C8:C18) -> 250.29 | D19: =SUM(D8:D18) -> 156.5 | E19: =SUM(E8:E18) -> 237.05 | F19: =SUM(F8:F18) -> 268.63 | G19: =SUM(G8:G18) -> 220
B20: Operating profit before working capital | C20: 2260.36 | D20: 2609.19 | E20: 3040.54 | F20: 3575.13 | G20: =G6+G19 -> 3679
B21: Adjustment for changes in working capital:
B22: (Increase) / decrease in operating assets:
B23: Inventories | C23: -622.09 | D23: -1380.05 | E23: -815.45 | F23: -1.89 | G23: -1432
B24: Trade receivables | C24: -103.69 | D24: -1138.18 | E24: -789.75 | F24: -1642.3 | G24: -2115
B25: Loans | C25: -48.73 | D25: -19.88 | E25: 28.66 | F25: -31.32 | G25: 0
B26: Other financial assets | C26: -0.62 | D26: -7.63 | E26: -46.75 | F26: -6.97 | G26: 0
B27: Other assets | C27: -256.28 | D27: 166.28 | E27: -83.95 | F27: -287.64 | G27: -423
B28: Increase / (decrease) in operating liabilities:
B29: Trade payables | C29: 183.62 | D29: 349.05 | E29: 301.28 | F29: 319.6 | G29: 722
B30: Other financial liabilities | C30: 47.76 | D30: -81.06 | E30: 110.27 | F30: 98.01 | G30: 0
B31: Other liabilities | C31: -192.03 | D31: 700.95 | E31: 295.86 | F31: 399.2 | G31: 1136
B32: Provisions | C32: 119.13 | D32: -211.94 | E32: 70.18 | F32: 117.12 | G32: 422
C33: =SUM(C23:C32) -> -872.93 | D33: =SUM(D23:D32) -> -1622.46 | E33: =SUM(E23:E32) -> -929.65 | F33: =SUM(F23:F32) -> -1036.19 | G33: =SUM(G23:G32) -> -1690
B34: Cash generated from operations | C34: 1387.43 | D34: 986.73 | E34: 2110.89 | F34: 2538.94 | G34: =G20+G33 -> 1989
B35: Income taxes paid (net of refunds) | C35: -762.57 | D35: -604.35 | E35: -695.92 | F35: -667.47 | G35: -1063
B37: Net cash flows generated from operating activities (A) | C37: 624.86 | D37: 382.38 | E37: 1414.97 | F37: 1871.47 | G37: =G34+G35 -> 926
A39: B. | B39: Cash flows from investing activities
B40: Purchase of property, plant and equipment
B41: and intangible assets | C41: -382.19 | D41: -1069.2 | E41: -932.76 | F41: -1005.5 | G41: -936
B42: Proceeds from disposal of property, plant
B43: and equipment | C43: 6.58 | D43: 15.72 | E43: 8.34 | F43: 10.67 | G43: 8
B44: Investment in fixed deposits | C44: -8411.75 | D44: -11525.43 | E44: -3098.26 | F44: -2589.2 | G44: 0
B45: Redemption of fixed deposits / Other investing inflows | C45: 8597.07 | D45: 12215.12 | E45: 3838.88 | F45: 1863.91 | G45: 1105
B46: Interest received | C46: 191.72 | D46: 204.14 | E46: 189.8 | F46: 208.52 | G46: 253
B47: Income from trade investments (non-current) | C47: 26.83 | D47: 32.34 | E47: 39.32 | F47: 47.41 | G47: 67
B48: Net cash flows generated from/(used in) investing activities (B) | C48: 28.26 | D48: -127.31 | E48: 45.32 | F48: -1464.19 | G48: =SUM(G41:G47) -> 497
A51: C. | B51: Cash flows from financing activities
B52: Proceeds from current borrowings | C52: 800 | D52: 580 | E52: 400 | F52: 500 | G52: 0
B53: Repayment of current borrowings | C53: -1400 | D53: -580 | E53: -400 | F53: -500 | G53: 0
B54: Interest paid | C54: -47.69 | D54: -58.39 | E54: -49.92 | F54: -23.87 | G54: -14
B55: Repayment of lease liabilities | C55: -10.65 | D55: -12.13 | E55: -13.15 | F55: -15.07 | G55: -11
B56: Dividends paid | C56: -295.87 | D56: -435.1 | E56: -522.12 | F56: -609.14 | G56: -696
B57: Net cash flows used in financing activities (C) | C57: -954.21 | D57: -505.62 | E57: -585.19 | F57: -648.08 | G57: -721
B58: Net decrease in Cash and cash equivalents (A+B+C) | C58: -301.09 | D58: -250.55 | E58: 875.1 | F58: -240.8 | G58: 702
B60: Cash and cash equivalents at the beginning of the year | C60: 870.68 | D60: 565.65 | E60: 319.54 | F60: 1195.28 | G60: 959
B61: Effects of exchange rate changes on cash and cash equivalents | C61: -3.94 | D61: 4.44 | E61: 0.64 | F61: 4.53 | G61: 7
B62: Cash and cash equivalents at the end of the year | C62: 565.65 | D62: 319.54 | E62: 1195.28 | F62: 959.01 | G62: 1668

Sheet Model
A1: KSB LTD | F1: Historical Period | M1: Forecasting Period
A2: Financial Statement & DCF Analysis | H2: 2021 | I2: =H2+1 -> 2022 | J2: =I2+1 -> 2023 | K2: =J2+1 -> 2024 | L2: =K2+1 -> 2025 | M2: =L2+1 -> 2026 | N2: =M2+1 -> 2027 | O2: =N2+1 -> 2028 | P2: =O2+1 -> 2029 | Q2: =P2+1 -> 2030
D3: Master check | H3: =IF(H73>1,"Error","OK") -> OK | I3: =IF(I73>1,"Error","OK") -> OK | J3: =IF(J73>1,"Error","OK") -> OK | K3: =IF(K73>1,"Error","OK") -> OK | L3: =IF(L73>1,"Error","OK") -> OK | M3: =IF(M73>1,"Error","OK") -> OK | N3: =IF(N73>1,"Error","OK") -> OK | O3: =IF(O73>1,"Error","OK") -> OK | ... Q3: =IF(Q73>1,"Error","OK") -> OK
A5: Ratio & Assumptions
D7: Scenario | E7: Base Case | F7: Units | G7: =IF(E7=Scenario!B5,1,IF(Model!E7=Scenario!B6,2,3)) -> 1
D8: Revenue Growth Rate | F8: % | H8: N/A | I8: =I25/H25-1 -> 0.21683761 | J8: =J25/I25-1 -> 0.23341786 | K8: =K25/J25-1 -> 0.1271997 | L8: =L25/K25-1 -> 0.064196004 | M8: {=CHOOSE(G7,Scenario!F5:J5,Scenario!F6:J6,Scenario!F7:J7)} -> 0.08 | N8: 0.068 | O8: 0.0578 | P8: 0.04913 | Q8: 0.0417605
D9: COGS (% of Revenue) | F9: % | H9: =-(H26/H25) -> 0.52923914 | I9: =-(I26/I25) -> 0.54227371 | J9: =-(J26/J25) -> 0.56848006 | K9: =-(K26/K25) -> 0.56142744 | L9: =-(L26/L25) -> 0.54023074 | M9: =AVERAGE(H9:L9) -> 0.54833022 | N9: =M9 -> 0.54833022 | O9: =N9 -> 0.54833022 | P9: =O9 -> 0.54833022 | Q9: =P9 -> 0.54833022
D10: Salary (% of Revenue) | F10: % | H10: =-(H29/H25) -> 0.14384311 | I10: =-(I29/I25) -> 0.13386518 | J10: =-(J29/J25) -> 0.12000643 | K10: =-(K29/K25) -> 0.12376958 | L10: =-(L29/L25) -> 0.13514115 | M10: =AVERAGE(H10:L10) -> 0.13132509 | N10: =M10 -> 0.13132509 | O10: =N10 -> 0.13132509 | P10: =O10 -> 0.13132509 | Q10: =P10 -> 0.13132509
D11: Other SG&A (% of Revenue) | F11: % | H11: =-H30/H25 -> 0.18702043 | I11: =-I30/I25 -> 0.18848548 | J11: =-J30/J25 -> 0.18087759 | K11: =-K30/K25 -> 0.18155286 | L11: =-L30/L25 -> 0.18607412 | M11: =AVERAGE(H11:L11) -> 0.18480209 | N11: =M11 -> 0.18480209 | O11: =N11 -> 0.18480209 | P11: =O11 -> 0.18480209 | Q11: =P11 -> 0.18480209
D12: Depreciation & Amortization (% of PPE) | F12: % | I12: =-I32/I118 -> 0.12938627 | J12: =-J32/J118 -> 0.13239699 | K12: =-K32/K118 -> 0.12034852 | L12: =-L32/L118 -> 0.1182268 | M12: =AVERAGE(H12:L12) -> 0.12508965 | N12: =M12 -> 0.12508965 | O12: =N12 -> 0.12508965 | P12: =O12 -> 0.12508965 | Q12: =P12 -> 0.12508965
D13: Interest (% of debt) | F13: % | I13: =-I34/I124 -> 2.0495149 | J13: =-J34/J124 -> 1.8355309 | K13: =-K34/K124 -> 0.83961681 | L13: =-L34/L124 -> 0.87310827 | M13: 0.07 | N13: 0.07 | O13: 0.07 | P13: 0.07 | Q13: 0.07
D14: Other Income (Expenses)(% of Revenue) | F14: % | H14: =H35/H25 -> 0.026791051 | I14: =I35/I25 -> 0.027446816 | J14: =J35/J25 -> 0.018577027 | K14: =K35/K25 -> 0.019800749 | L14: =L35/L25 -> 0.012501391 | M14: =AVERAGE(H14:L14) -> 0.021023407 | N14: =M14 -> 0.021023407 | O14: =N14 -> 0.021023407 | P14: =O14 -> 0.021023407 | Q14: =P14 -> 0.021023407
D15: Taxes Rate (% of Earning Before Tax) | F15: % | H15: =-H37/H36 -> 0.25679703 | I15: =-I37/I36 -> 0.25493642 | J15: =-J37/J36 -> 0.25545302 | K15: =-K37/K36 -> 0.25154998 | L15: =-L37/L36 -> 0.26019081 | M15: =AVERAGE(H15:L15) -> 0.25578545 | N15: =M15 -> 0.25578545 | O15: =N15 -> 0.25578545 | P15: =O15 -> 0.25578545 | Q15: =P15 -> 0.25578545
D16: Divident Payout Ratio | F16: % | H16: =-H98/H38 -> 0.1980534 | I16: =-I98/I38 -> 0.23809654 | J16: =-J98/J38 -> 0.25013774 | K16: =-K98/K38 -> 0.24614203 | L16: =-L98/L38 -> 0.27198124 | M16: =AVERAGE(H16:L16) -> 0.24088219 | N16: =M16 -> 0.24088219 | O16: =N16 -> 0.24088219 | P16: =O16 -> 0.24088219 | Q16: =P16 -> 0.24088219
D17: Account Recievable | F17: Days | H17: =H47/H25*365 -> 67.764913 | I17: =I47/I25*365 -> 80.865302 | J17: =J47/J25*365 -> 79.865789 | K17: =K47/K25*365 -> 93.699797 | L17: =L47/L25*365 -> 117.6904 | M17: 110 | N17: 105 | O17: 100 | P17: 96 | Q17: 93
D18: Inventory | F18: Days | H18: =-H48/H26*365 -> 194.87732 | I18: =-I48/I26*365 -> 207.28469 | J18: =-J48/J26*365 -> 183.60828 | K18: =-K48/K26*365 -> 164.98357 | L18: =-L48/L26*365 -> 197.02431 | M18: =AVERAGE(H18:L18) -> 189.55563 | N18: =M18 -> 189.55563 | O18: =N18 -> 189.55563 | P18: =O18 -> 189.55563 | Q18: =P18 -> 189.55563
D19: Account Payable | F19: Days | H19: =-H60/H26*365 -> 128.58198 | I19: =-I60/I26*365 -> 116.10055 | J19: =-J60/J26*365 -> 98.072089 | K19: =-K60/K26*365 -> 96.332534 | L19: =-L60/L26*365 -> 110.6053 | M19: =AVERAGE(H19:L19) -> 109.93849 | N19: =M19 -> 109.93849 | O19: =N19 -> 109.93849 | P19: =O19 -> 109.93849 | Q19: =P19 -> 109.93849
D20: Capital Asset Turnover Ratio | F20: Times | H20: =H25/H52 -> 4.2802612 | I20: =I25/I52 -> 4.8557113 | J20: =J25/J52 -> 4.9784953 | K20: =K25/K52 -> 5.1368551 | L20: =L25/L52 -> 5.1890279 | M20: =L20+0.02 -> 5.2090279 | N20: =M20+0.02 -> 5.2290279 | O20: =N20+0.02 -> 5.2490279 | P20: =O20+0.02 -> 5.2690279 | Q20: =P20+0.02 -> 5.2890279
A23: Income Statement
B24: Income
D25: Revenue | F25: ₹ in MM | H25: ='P&L'!B5 -> 14972.91 | I25: ='P&L'!C5 -> 18219.6 | J25: ='P&L'!D5 -> 22472.38 | K25: ='P&L'!E5 -> 25330.86 | L25: ='P&L'!F5 -> 26957 | M25: =L25*(1+M8) -> 29113.56 | N25: =M25*(1+N8) -> 31093.282 | O25: =N25*(1+O8) -> 32890.474 | P25: =O25*(1+P8) -> 34506.383 | Q25: =P25*(1+Q8) -> 35947.387
D26: Cost of Good Solds (COGS) | F26: ₹ in MM | H26: =-('P&L'!B9+'P&L'!B10+'P&L'!B12) -> -7924.25 | I26: =-('P&L'!C9+'P&L'!C10+'P&L'!C12) -> -9880.01 | J26: =-('P&L'!D9+'P&L'!D10+'P&L'!D12) -> -12775.1 | K26: =-('P&L'!E9+'P&L'!E10+'P&L'!E12) -> -14221.44 | L26: =-('P&L'!F9+'P&L'!F10+'P&L'!F12) -> -14563 | M26: =-M25*M9 -> -15963.845 | N26: =-N25*N9 -> -17049.386 | O26: =-O25*O9 -> -18034.841 | P26: =-P25*P9 -> -18920.892 | Q26: =-Q25*Q9 -> -19711.038
D27: Gross Profit | F27: ₹ in MM | H27: =SUM(H25:H26) -> 7048.66 | I27: =SUM(I25:I26) -> 8339.59 | J27: =SUM(J25:J26) -> 9697.28 | K27: =SUM(K25:K26) -> 11109.42 | L27: =SUM(L25:L26) -> 12394 | M27: =SUM(M25:M26) -> 13149.715 | N27: =SUM(N25:N26) -> 14043.896 | O27: =SUM(O25:O26) -> 14855.633 | ... Q27: =SUM(Q25:Q26) -> 16236.348
B28: Expenses
D29: Salaries & Benefits | F29: ₹ in MM | H29: =-'P&L'!B13 -> -2153.75 | I29: =-'P&L'!C13 -> -2438.97 | J29: =-'P&L'!D13 -> -2696.83 | K29: =-'P&L'!E13 -> -3135.19 | L29: =-'P&L'!F13 -> -3643 | M29: =-M25*M10 -> -3823.3409 | N29: =-N25*N10 -> -4083.3281 | O29: =-O25*O10 -> -4319.3444 | P29: =-P25*P10 -> -4531.5538 | Q29: =-Q25*Q10 -> -4720.7938
D30: Other SG&A Expenses | F30: ₹ in MM | H30: =-'P&L'!B16 -> -2800.24 | I30: =-'P&L'!C16 -> -3434.13 | J30: =-'P&L'!D16 -> -4064.75 | K30: =-'P&L'!E16 -> -4598.89 | L30: =-'P&L'!F16 -> -5016 | M30: =-(M25*M11) -> -5380.2469 | N30: =-(N25*N11) -> -5746.1036 | O30: =-(O25*O11) -> -6078.2284 | P30: =-(P25*P11) -> -6376.8518 | Q30: =-(Q25*Q11) -> -6643.1523
D31: EBITDA | F31: ₹ in MM | H31: =SUM(H27:H30) -> 2094.67 | I31: =SUM(I27:I30) -> 2466.49 | J31: =SUM(J27:J30) -> 2935.7 | K31: =SUM(K27:K30) -> 3375.34 | L31: =SUM(L27:L30) -> 3735 | M31: =SUM(M27:M30) -> 3946.1275 | N31: =SUM(N27:N30) -> 4214.4642 | O31: =SUM(O27:O30) -> 4458.0602 | ... Q31: =SUM(Q27:Q30) -> 4872.4021
D32: Depreciation & Amortization Expenses | F32: ₹ in MM | H32: =-'P&L'!B15 -> -435.34 | I32: =-'P&L'!C15 -> -452.61 | J32: =-'P&L'!D15 -> -496.78 | K32: =-'P&L'!E15 -> -543.24 | L32: =-'P&L'!F15 -> -583 | M32: =M120 -> -649.84072 | N32: =N120 -> -620.34003 | O32: =O120 -> -590.10114 | P32: =P120 -> -559.11449 | Q32: =Q120 -> -527.53764
D33: EBIT | F33: ₹ in MM | H33: =SUM(H31:H32) -> 1659.33 | I33: =SUM(I31:I32) -> 2013.88 | J33: =SUM(J31:J32) -> 2438.92 | K33: =SUM(K31:K32) -> 2832.1 | L33: =SUM(L31:L32) -> 3152 | M33: =SUM(M31:M32) -> 3296.2868 | N33: =SUM(N31:N32) -> 3594.1242 | O33: =SUM(O31:O32) -> 3867.9591 | ... Q33: =SUM(Q31:Q32) -> 4344.8645
D34: Interest | F34: ₹ in MM | H34: =-'P&L'!B14 -> -50.4 | I34: =-'P&L'!C14 -> -61.26 | J34: =-'P&L'!D14 -> -52.9 | K34: =-'P&L'!E14 -> -27.17 | L34: =-'P&L'!F14 -> -30 | M34: =M127 -> -2.94 | N34: =N127 -> -2.94 | O34: =O127 -> -2.94 | P34: =P127 -> -2.94 | Q34: =Q127 -> -2.94
D35: Other Income (Expenses) | F35: ₹ in MM | H35: ='P&L'!B6+'P&L'!B21 -> 401.14 | I35: ='P&L'!C6+'P&L'!C21 -> 500.07 | J35: ='P&L'!D6+'P&L'!D21 -> 417.47 | K35: ='P&L'!E6+'P&L'!E21 -> 501.57 | L35: ='P&L'!F6+'P&L'!F21 -> 337 | M35: =M25*M14 -> 612.06621 | N35: =N25*N14 -> 653.68671 | O35: =O25*O14 -> 691.46981 | P35: =P25*P14 -> 725.44172 | Q35: =Q25*Q14 -> 755.73653
D36: Earning Before Tax | F36: ₹ in MM | H36: =SUM(H33:H35) -> 2010.07 | I36: =SUM(I33:I35) -> 2452.69 | J36: =SUM(J33:J35) -> 2803.49 | K36: =SUM(K33:K35) -> 3306.5 | L36: =SUM(L33:L35) -> 3459 | M36: =SUM(M33:M35) -> 3905.413 | N36: =SUM(N33:N35) -> 4244.8709 | O36: =SUM(O33:O35) -> 4556.4889 | ... Q36: =SUM(Q33:Q35) -> 5097.661
D37: Taxes | F37: ₹ in MM | H37: =-'P&L'!B26 -> -516.18 | I37: =-'P&L'!C26 -> -625.28 | J37: =-'P&L'!D26 -> -716.16 | K37: =-'P&L'!E26 -> -831.75 | L37: =-'P&L'!F26 -> -900 | M37: =-M36*M15 -> -998.94783 | N37: =-N36*N15 -> -1085.7762 | O37: =-O36*O15 -> -1165.4836 | P37: =-P36*P15 -> -1238.1223 | Q37: =-Q36*Q15 -> -1303.9075
D38: Net Earing | F38: ₹ in MM | H38: =SUM(H36:H37) -> 1493.89 | I38: =SUM(I36:I37) -> 1827.41 | J38: =SUM(J36:J37) -> 2087.33 | K38: =SUM(K36:K37) -> 2474.75 | L38: =SUM(L36:L37) -> 2559 | M38: =SUM(M36:M37) -> 2906.4652 | N38: =SUM(N36:N37) -> 3159.0947 | O38: =SUM(O36:O37) -> 3391.0053 | ... Q38: =SUM(Q36:Q37) -> 3793.7535
A41: Balance Sheet
B43: Asset
C44: Current Asset :
D45: Cash | F45: ₹ in MM | H45: ='Balance Sheet'!C24 -> 565.65 | I45: ='Balance Sheet'!D24 -> 319.54 | J45: ='Balance Sheet'!E24 -> 1195.28 | K45: ='Balance Sheet'!F24 -> 959.01 | L45: ='Balance Sheet'!G24 -> 1668 | M45: =M71-(M46+M47+M48+M49+M52+M53+M54+M55) -> 4261.1763 | N45: =N71-(N46+N47+N48+N49+N52+N53+N54+N55) -> 6738.7737 | O45: =O71-(O46+O47+O48+O49+O52+O53+O54+O55) -> 9501.8667 | P45: =P71-(P46+P47+P48+P49+P52+P53+P54+P55) -> 12431.225 | Q45: =Q71-(Q46+Q47+Q48+Q49+Q52+Q53+Q54+Q55) -> 15488.806
D46: Bank Deposits | F46: ₹ in MM | H46: ='Balance Sheet'!C25 -> 2979.65 | I46: ='Balance Sheet'!D25 -> 2290.53 | J46: ='Balance Sheet'!E25 -> 1550.4 | K46: ='Balance Sheet'!F25 -> 2275.67 | L46: ='Balance Sheet'!G25 -> 1166 | M46: =L46 -> 1166 | N46: =M46 -> 1166 | O46: =N46 -> 1166 | P46: =O46 -> 1166 | Q46: =P46 -> 1166
D47: Account Receivable | F47: ₹ in MM | H47: ='Balance Sheet'!C23 -> 2779.83 | I47: ='Balance Sheet'!D23 -> 4036.53 | J47: ='Balance Sheet'!E23 -> 4917.19 | K47: ='Balance Sheet'!F23 -> 6502.73 | L47: ='Balance Sheet'!G23 -> 8692 | M47: =M25*M17/365 -> 8773.9496 | N47: =N25*N17/365 -> 8944.6428 | O47: =O25*O17/365 -> 9011.0887 | P47: =P25*P17/365 -> 9075.6514 | Q47: =Q25*Q17/365 -> 9159.1971
D48: Inventory | F48: ₹ in MM | H48: ='Balance Sheet'!C21 -> 4230.84 | I48: ='Balance Sheet'!D21 -> 5610.89 | J48: ='Balance Sheet'!E21 -> 6426.34 | K48: ='Balance Sheet'!F21 -> 6428.23 | L48: ='Balance Sheet'!G21 -> 7861 | M48: =-M26*M18/365 -> 8290.5115 | N48: =-N26*N18/365 -> 8854.2663 | O48: =-O26*O18/365 -> 9366.0429 | P48: =-P26*P18/365 -> 9826.1966 | Q48: =-Q26*Q18/365 -> 10236.543
D49: Other Current Assets | F49: ₹ in MM | H49: ='Balance Sheet'!C28 -> 517.95 | I49: ='Balance Sheet'!D28 -> 351.35 | J49: ='Balance Sheet'!E28 -> 429.43 | K49: ='Balance Sheet'!F28 -> 701.81 | L49: ='Balance Sheet'!G28 -> 1113 | M49: =L49*(M25/L25) -> 1202.04 | N49: =M49*(N25/M25) -> 1283.7787 | O49: =N49*(O25/N25) -> 1357.9811 | P49: =O49*(P25/O25) -> 1424.6987 | Q49: =P49*(Q25/P25) -> 1484.1949
C51: Non Current Assets :
D52: Property & equipment | F52: ₹ in MM | H52: ='Balance Sheet'!C6+'Balance Sheet'!C7+'Balance Sheet'!C8+'Balance Sheet'!C9+'Balance Sheet'!C10 -> 3498.13 | I52: ='Balance Sheet'!D6+'Balance Sheet'!D7+'Balance Sheet'!D8+'Balance Sheet'!D9+'Balance Sheet'!D10 -> 3752.2 | J52: ='Balance Sheet'!E6+'Balance Sheet'!E7+'Balance Sheet'!E8+'Balance Sheet'!E9+'Balance Sheet'!E10 -> 4513.89 | K52: ='Balance Sheet'!F6+'Balance Sheet'!F7+'Balance Sheet'!F8+'Balance Sheet'!F9+'Balance Sheet'!F10 -> 4931.2 | L52: ='Balance Sheet'!G6+'Balance Sheet'!G7+'Balance Sheet'!G8+'Balance Sheet'!G9+'Balance Sheet'!G10 -> 5195 | M52: =M121 -> 4959.1636 | N52: =N121 -> 4717.4259 | O52: =O121 -> 4469.7104 | P52: =P121 -> 4217.2765 | Q52: =Q121 -> 3962.1904
D53: Godwill | F53: ₹ in MM | H53: =0 -> 0 | I53: =0 -> 0 | J53: =0 -> 0 | K53: =0 -> 0 | L53: =0 -> 0 | M53: =0 -> 0 | N53: =0 -> 0 | O53: =0 -> 0 | ... Q53: =0 -> 0
D54: Financial Assets | F54: ₹ in MM | H54: ='Balance Sheet'!C12+'Balance Sheet'!C13+'Balance Sheet'!C14+'Balance Sheet'!C26+'Balance Sheet'!C27+'Balance Sheet'!C15 -> 1144.53 | I54: ='Balance Sheet'!D12+'Balance Sheet'!D13+'Balance Sheet'!D14+'Balance Sheet'!D26+'Balance Sheet'!D27+'Balance Sheet'!D15 -> 1106.65 | J54: ='Balance Sheet'!E12+'Balance Sheet'!E13+'Balance Sheet'!E14+'Balance Sheet'!E26+'Balance Sheet'!E27+'Balance Sheet'!E15 -> 1096.6 | K54: ='Balance Sheet'!F12+'Balance Sheet'!F13+'Balance Sheet'!F14+'Balance Sheet'!F26+'Balance Sheet'!F27+'Balance Sheet'!F15 -> 1225.28 | L54: ='Balance Sheet'!G12+'Balance Sheet'!G13+'Balance Sheet'!G14+'Balance Sheet'!G26+'Balance Sheet'!G27+'Balance Sheet'!G15 -> 1386 | M54: =L54*(M25/L25) -> 1496.88 | N54: =M54*(N25/M25) -> 1598.6678 | O54: =N54*(O25/N25) -> 1691.0708 | P54: =O54*(P25/O25) -> 1774.1532 | Q54: =P54*(Q25/P25) -> 1848.2427
D55: Other Non Current Assets | F55: ₹ in MM | H55: ='Balance Sheet'!C16+'Balance Sheet'!C17+'Balance Sheet'!C18 -> 377.16 | I55: ='Balance Sheet'!D16+'Balance Sheet'!D17+'Balance Sheet'!D18 -> 780.43 | J55: ='Balance Sheet'!E16+'Balance Sheet'!E17+'Balance Sheet'!E18 -> 528.3 | K55: ='Balance Sheet'!F16+'Balance Sheet'!F17+'Balance Sheet'!F18 -> 456.35 | L55: ='Balance Sheet'!G16+'Balance Sheet'!G17+'Balance Sheet'!G18 -> 845 | M55: =L55*(M25/L25) -> 912.6 | N55: =M55*(N25/M25) -> 974.6568 | O55: =N55*(O25/N25) -> 1030.992 | P55: =O55*(P25/O25) -> 1081.6446 | Q55: =P55*(Q25/P25) -> 1126.8146
D56: Total Assets | F56: ₹ in MM | H56: =SUM(H45:H55) -> 16093.74 | I56: =SUM(I45:I55) -> 18248.12 | J56: =SUM(J45:J55) -> 20657.43 | K56: =SUM(K45:K55) -> 23480.28 | L56: =SUM(L45:L55) -> 27926 | M56: =SUM(M45:M55) -> 31062.321 | N56: =SUM(N45:N55) -> 34278.212 | O56: =SUM(O45:O55) -> 37594.753 | ... Q56: =SUM(Q45:Q55) -> 44471.989
B58: Liabilities
C59: Current Liabilities :
D60: Account Payable | F60: ₹ in MM | H60: ='Balance Sheet'!C47+'Balance Sheet'!C49 -> 2791.55 | I60: ='Balance Sheet'!D47+'Balance Sheet'!D49 -> 3142.67 | J60: ='Balance Sheet'!E47+'Balance Sheet'!E49 -> 3432.55 | K60: ='Balance Sheet'!F47+'Balance Sheet'!F49 -> 3753.39 | L60: ='Balance Sheet'!G47+'Balance Sheet'!G49 -> 4413 | M60: =-M26*M19/365 -> 4808.3314 | N60: =-N26*N19/365 -> 5135.298 | O60: =-O26*O19/365 -> 5432.1182 | P60: =-P26*P19/365 -> 5698.9982 | Q60: =-Q26*Q19/365 -> 5936.9912
D61: Other Current Liabilities | F61: ₹ in MM | H61: ='Balance Sheet'!C51+'Balance Sheet'!C52+'Balance Sheet'!C53+'Balance Sheet'!C54 -> 2647.25 | I61: ='Balance Sheet'!D51+'Balance Sheet'!D52+'Balance Sheet'!D53+'Balance Sheet'!D54 -> 3199.49 | J61: ='Balance Sheet'!E51+'Balance Sheet'!E52+'Balance Sheet'!E53+'Balance Sheet'!E54 -> 3721.03 | K61: ='Balance Sheet'!F51+'Balance Sheet'!F52+'Balance Sheet'!F53+'Balance Sheet'!F54 -> 4246.38 | L61: ='Balance Sheet'!G51+'Balance Sheet'!G52+'Balance Sheet'!G53+'Balance Sheet'!G54 -> 5832 | M61: =L61*(M25/L25) -> 6298.56 | N61: =M61*(N25/M25) -> 6726.8621 | O61: =N61*(O25/N25) -> 7115.6747 | P61: =O61*(P25/O25) -> 7465.2678 | Q61: =P61*(Q25/P25) -> 7777.0211
C62: Non- Current Liabilities | F62: ₹ in MM
D63: Debt | F63: ₹ in MM | H63: ='Balance Sheet'!C45+'Balance Sheet'!C39 -> 29.89 | I63: ='Balance Sheet'!D45+'Balance Sheet'!D39 -> 28.82 | J63: ='Balance Sheet'!E45+'Balance Sheet'!E39 -> 32.36 | K63: ='Balance Sheet'!F45+'Balance Sheet'!F39 -> 34.36 | L63: ='Balance Sheet'!G45+'Balance Sheet'!G39 -> 42 | M63: =L63 -> 42 | N63: =M63 -> 42 | O63: =N63 -> 42 | P63: =O63 -> 42 | Q63: =P63 -> 42
D64: Other Non Current Liabilities | F64: ₹ in MM | H64: ='Balance Sheet'!C40+'Balance Sheet'!C41 -> 516.67 | I64: ='Balance Sheet'!D40+'Balance Sheet'!D41 -> 445.98 | J64: ='Balance Sheet'!E40+'Balance Sheet'!E41 -> 452.4 | K64: ='Balance Sheet'!F40+'Balance Sheet'!F41 -> 592.65 | L64: ='Balance Sheet'!G40+'Balance Sheet'!G41 -> 851 | M64: =L64*(M25/L25) -> 919.08 | N64: =M64*(N25/M25) -> 981.57744 | O64: =N64*(O25/N25) -> 1038.3126 | P64: =O64*(P25/O25) -> 1089.3249 | Q64: =P64*(Q25/P25) -> 1134.8157
D65: Total Liabilities | F65: ₹ in MM | H65: =SUM(H60:H64) -> 5985.36 | I65: =SUM(I60:I64) -> 6816.96 | J65: =SUM(J60:J64) -> 7638.34 | K65: =SUM(K60:K64) -> 8626.78 | L65: =SUM(L60:L64) -> 11138 | M65: =SUM(M60:M64) -> 12067.971 | N65: =SUM(N60:N64) -> 12885.738 | O65: =SUM(O60:O64) -> 13628.106 | ... Q65: =SUM(Q60:Q64) -> 14890.828
C66: Shareholder Equity
D67: Equity Capital | F67: ₹ in MM | H67: ='Balance Sheet'!C33 -> 348.08 | I67: ='Balance Sheet'!D33 -> 348.08 | J67: ='Balance Sheet'!E33 -> 348.08 | K67: ='Balance Sheet'!F33 -> 348.08 | L67: ='Balance Sheet'!G33 -> 348.08 | M67: =L67 -> 348.08 | N67: =M67 -> 348.08 | O67: =N67 -> 348.08 | P67: =O67 -> 348.08 | Q67: =P67 -> 348.08
D68: Retained Earning | F68: ₹ in MM | H68: ='Balance Sheet'!C34 -> 9760.3 | I68: ='Balance Sheet'!D34 -> 11083.08 | J68: ='Balance Sheet'!E34 -> 12671.01 | K68: ='Balance Sheet'!F34 -> 14505.42 | L68: ='Balance Sheet'!G34 -> 16439.92 | M68: =L68+M38+M98 -> 18646.269 | N68: =M68+N38+N98 -> 21044.395 | O68: =N68+O38+O98 -> 23618.567 | P68: =O68+P38+P98 -> 26353.175 | Q68: =P68+Q38+Q98 -> 29233.081
D69: Total Shareholder Equity | F69: ₹ in MM | H69: =SUM(H67:H68) -> 10108.38 | I69: =SUM(I67:I68) -> 11431.16 | J69: =SUM(J67:J68) -> 13019.09 | K69: =SUM(K67:K68) -> 14853.5 | L69: =SUM(L67:L68) -> 16788 | M69: =SUM(M67:M68) -> 18994.349 | N69: =SUM(N67:N68) -> 21392.475 | O69: =SUM(O67:O68) -> 23966.647 | ... Q69: =SUM(Q67:Q68) -> 29581.161
D70: Non- Controlling Interest | F70: ₹ in MM | H70: 0 | I70: 0 | J70: 0 | K70: 0 | L70: 0 | M70: 0 | N70: 0 | O70: 0 | P70: 0 | Q70: 0
D71: Total Liabilities & Shareholder Equity | F71: ₹ in MM | H71: =SUM(H65,H69) -> 16093.74 | I71: =SUM(I65,I69) -> 18248.12 | J71: =SUM(J65,J69) -> 20657.43 | K71: =SUM(K65,K69) -> 23480.28 | L71: =SUM(L65,L69) -> 27926 | M71: =SUM(M65,M69) -> 31062.321 | N71: =SUM(N65,N69) -> 34278.212 | O71: =SUM(O65,O69) -> 37594.753 | ... Q71: =SUM(Q65,Q69) -> 44471.989
D73: Check | H73: =ABS(H56-H71) -> 3.6379788e-12 | I73: =ABS(I56-I71) -> 3.6379788e-12 | J73: =ABS(J56-J71) -> 3.6379788e-12 | K73: =ABS(K56-K71) -> 0 | L73: =ABS(L56-L71) -> 0 | M73: =ABS(M56-M71) -> 3.6379788e-12 | N73: =ABS(N56-N71) -> 7.2759576e-12 | O73: =ABS(O56-O71) -> 7.2759576e-12 | ... Q73: =ABS(Q56-Q71) -> 7.2759576e-12
A77: Cash Flow Statement
C79: Operating Cash Flow
D80: Net Earings | F80: ₹ in MM | H80: ='C&F'!C6 -> 2010.07 | I80: ='C&F'!D6 -> 2452.69 | J80: ='C&F'!E6 -> 2803.49 | K80: ='C&F'!F6 -> 3306.5 | L80: ='C&F'!G6 -> 3459 | M80: =M38 -> 2906.4652 | N80: =N38 -> 3159.0947 | O80: =O38 -> 3391.0053 | P80: =P38 -> 3602.3497 | Q80: =Q38 -> 3793.7535
D81: Plus: Depreciation & Amortization | F81: ₹ in MM | H81: ='C&F'!C8 -> 435.34 | I81: ='C&F'!D8 -> 452.61 | J81: ='C&F'!E8 -> 496.78 | K81: ='C&F'!F8 -> 543.24 | L81: ='C&F'!G8 -> 583 | M81: =-M32 -> 649.84072 | N81: =-N32 -> 620.34003 | O81: =-O32 -> 590.10114 | P81: =-P32 -> 559.11449 | Q81: =-Q32 -> 527.53764
D82: Plus/Less : Adjustment for non-operating item | F82: ₹ in MM | H82: ='C&F'!C9+'C&F'!C11+'C&F'!C12+'C&F'!C13+'C&F'!C15+'C&F'!C16+'C&F'!C17+'C&F'!C18 -> -185.05 | I82: ='C&F'!D9+'C&F'!D11+'C&F'!D12+'C&F'!D13+'C&F'!D15+'C&F'!D16+'C&F'!D17+'C&F'!D18 -> -296.11 | J82: ='C&F'!E9+'C&F'!E11+'C&F'!E12+'C&F'!E13+'C&F'!E15+'C&F'!E16+'C&F'!E17+'C&F'!E18 -> -259.73 | K82: ='C&F'!F9+'C&F'!F11+'C&F'!F12+'C&F'!F13+'C&F'!F15+'C&F'!F16+'C&F'!F17+'C&F'!F18 -> -274.61 | L82: ='C&F'!G9+'C&F'!G11+'C&F'!G12+'C&F'!G13+'C&F'!G15+'C&F'!G16+'C&F'!G17+'C&F'!G18 -> -363 | M82: =-M34-M35 -> -609.12621 | N82: =-N34-N35 -> -650.74671 | O82: =-O34-O35 -> -688.52981 | P82: =-P34-P35 -> -722.50172 | Q82: =-Q34-Q35 -> -752.79653
D83: Plus/Less : Adjustment for operating Asset & liabities | F83: ₹ in MM | H83: ='C&F'!C23+'C&F'!C24+'C&F'!C25+'C&F'!C26+'C&F'!C27+'C&F'!C29+'C&F'!C30+'C&F'!C31+'C&F'!C32+'C&F'!C35 -> -1635.5 | I83: ='C&F'!D23+'C&F'!D24+'C&F'!D25+'C&F'!D26+'C&F'!D27+'C&F'!D29+'C&F'!D30+'C&F'!D31+'C&F'!D32+'C&F'!D35 -> -2226.81 | J83: ='C&F'!E23+'C&F'!E24+'C&F'!E25+'C&F'!E26+'C&F'!E27+'C&F'!E29+'C&F'!E30+'C&F'!E31+'C&F'!E32+'C&F'!E35 -> -1625.57 | K83: ='C&F'!F23+'C&F'!F24+'C&F'!F25+'C&F'!F26+'C&F'!F27+'C&F'!F29+'C&F'!F30+'C&F'!F31+'C&F'!F32+'C&F'!F35 -> -1703.66 | L83: ='C&F'!G23+'C&F'!G24+'C&F'!G25+'C&F'!G26+'C&F'!G27+'C&F'!G29+'C&F'!G30+'C&F'!G31+'C&F'!G32+'C&F'!G35 -> -2753 | M83: =M115 -> 261.39035 | N83: =N115 -> -60.918085 | O83: =O115 -> 33.207932 | P83: =P115 -> 25.039118 | Q83: =Q115 -> -3.642451
D84: Cash From Operation | F84: ₹ in MM | H84: =SUM(H80:H83) -> 624.86 | I84: =SUM(I80:I83) -> 382.38 | J84: =SUM(J80:J83) -> 1414.97 | K84: =SUM(K80:K83) -> 1871.47 | L84: =SUM(L80:L83) -> 926 | M84: =SUM(M80:M83) -> 3208.5701 | N84: =SUM(N80:N83) -> 3067.7699 | O84: =SUM(O80:O83) -> 3325.7846 | ... Q84: =SUM(Q80:Q83) -> 3564.8522
C86: Investing Cash Flow | F86: ₹ in MM
D87: Investment in Property & Equipnment | F87: ₹ in MM | H87: ='C&F'!C41 -> -382.19 | I87: ='C&F'!D41 -> -1069.2 | J87: ='C&F'!E41 -> -932.76 | K87: ='C&F'!F41 -> -1005.5 | L87: ='C&F'!G41 -> -936 | M87: =-M119 -> -414.00431 | N87: =-N119 -> -378.60232 | O87: =-O119 -> -342.38563 | P87: =-P119 -> -306.68066 | Q87: =-Q119 -> -272.45154
D88: Sale of Property, Plant and Equipnment | F88: ₹ in MM | H88: ='C&F'!C43 -> 6.58 | I88: ='C&F'!D43 -> 15.72 | J88: ='C&F'!E43 -> 8.34 | K88: ='C&F'!F43 -> 10.67 | L88: ='C&F'!G43 -> 8 | M88: 0 | N88: 0 | O88: 0 | P88: 0 | Q88: 0
D89: Net Proceed from sale of Investment | F89: ₹ in MM | H89: ='C&F'!C45+'C&F'!C44 -> 185.32 | I89: ='C&F'!D45+'C&F'!D44 -> 689.69 | J89: ='C&F'!E45+'C&F'!E44 -> 740.62 | K89: ='C&F'!F45+'C&F'!F44 -> -725.29 | L89: ='C&F'!G45+'C&F'!G44 -> 1105 | M89: =L54-M54 -> -110.88 | N89: =M54-N54 -> -101.78784 | O89: =N54-O54 -> -92.403001 | P89: =O54-P54 -> -83.08231 | Q89: =P54-Q54 -> -74.089523
D90: Dividend received | F90: ₹ in MM | H90: ='C&F'!C47 -> 26.83 | I90: ='C&F'!D47 -> 32.34 | J90: ='C&F'!E47 -> 39.32 | K90: ='C&F'!F47 -> 47.41 | L90: ='C&F'!G47 -> 67 | M90: 0 | N90: 0 | O90: 0 | P90: 0 | Q90: 0
D91: Interest received | F91: ₹ in MM | H91: ='C&F'!C46 -> 191.72 | I91: ='C&F'!D46 -> 204.14 | J91: ='C&F'!E46 -> 189.8 | K91: ='C&F'!F46 -> 208.52 | L91: ='C&F'!G46 -> 253 | M91: =M35 -> 612.06621 | N91: =N35 -> 653.68671 | O91: =O35 -> 691.46981 | P91: =P35 -> 725.44172 | Q91: =Q35 -> 755.73653
D92: Rent received | F92: ₹ in MM | H92: =0 -> 0 | I92: =0 -> 0 | J92: =0 -> 0 | K92: =0 -> 0 | L92: =0 -> 0 | M92: =0 -> 0 | N92: =0 -> 0 | O92: =0 -> 0 | ... Q92: =0 -> 0
D93: Cash From Investing | F93: ₹ in MM | H93: =SUM(H87:H92) -> 28.26 | I93: =SUM(I87:I92) -> -127.31 | J93: =SUM(J87:J92) -> 45.32 | K93: =SUM(K87:K92) -> -1464.19 | L93: =SUM(L87:L92) -> 497 | M93: =SUM(M87:M92) -> 87.181903 | N93: =SUM(N87:N92) -> 173.29656 | O93: =SUM(O87:O92) -> 256.68118 | ... Q93: =SUM(Q87:Q92) -> 409.19546
C95: Financing cash Flow
D96: Issuance(Repayment) of Debt | F96: ₹ in MM | H96: ='C&F'!C52+'C&F'!C53 -> -600 | I96: ='C&F'!D52+'C&F'!D53 -> 0 | J96: ='C&F'!E52+'C&F'!E53 -> 0 | K96: ='C&F'!F52+'C&F'!F53 -> 0 | L96: ='C&F'!G52+'C&F'!G53 -> 0 | M96: =M125 -> 0 | N96: =N125 -> 0 | O96: =O125 -> 0 | P96: =P125 -> 0 | Q96: =Q125 -> 0
D97: Issuance(Repayment) of Preferrance Share - NCI | F97: ₹ in MM | H97: 0 | I97: 0 | J97: 0 | K97: 0 | L97: 0 | M97: 0 | N97: 0 | O97: 0 | P97: 0 | Q97: 0
D98: Dividend Paid | F98: ₹ in MM | H98: ='C&F'!C56 -> -295.87 | I98: ='C&F'!D56 -> -435.1 | J98: ='C&F'!E56 -> -522.12 | K98: ='C&F'!F56 -> -609.14 | L98: ='C&F'!G56 -> -696 | M98: =-M38*M16 -> -700.11571 | N98: =-N38*N16 -> -760.96965 | O98: =-O38*O16 -> -816.8328 | P98: =-P38*P16 -> -867.74188 | Q98: =-Q38*Q16 -> -913.84766
D99: Interest Paid | F99: ₹ in MM | H99: ='C&F'!C54+'C&F'!C55 -> -58.34 | I99: ='C&F'!D54+'C&F'!D55 -> -70.52 | J99: ='C&F'!E54+'C&F'!E55 -> -63.07 | K99: ='C&F'!F54+'C&F'!F55 -> -38.94 | L99: ='C&F'!G54+'C&F'!G55 -> -25 | M99: =M127 -> -2.94 | N99: =N127 -> -2.94 | O99: =O127 -> -2.94 | P99: =P127 -> -2.94 | Q99: =Q127 -> -2.94
D100: Cash From Financing | F100: ₹ in MM | H100: =SUM(H96:H99) -> -954.21 | I100: =SUM(I96:I99) -> -505.62 | J100: =SUM(J96:J99) -> -585.19 | K100: =SUM(K96:K99) -> -648.08 | L100: =SUM(L96:L99) -> -721 | M100: =SUM(M96:M99) -> -703.05571 | N100: =SUM(N96:N99) -> -763.90965 | O100: =SUM(O96:O99) -> -819.7728 | ... Q100: =SUM(Q96:Q99) -> -916.78766
D102: Net Increase (Decrease) in Cash | F102: ₹ in MM | H102: =SUM(H84,H93,H100) -> -301.09 | I102: =SUM(I84,I93,I100) -> -250.55 | J102: =SUM(J84,J93,J100) -> 875.1 | K102: =SUM(K84,K93,K100) -> -240.8 | L102: =SUM(L84,L93,L100) -> 702 | M102: =SUM(M84,M93,M100) -> 2592.6963 | N102: =SUM(N84,N93,N100) -> 2477.1568 | O102: =SUM(O84,O93,O100) -> 2762.693 | ... Q102: =SUM(Q84,Q93,Q100) -> 3057.26
D103: Opening Cash Balance | F103: ₹ in MM | H103: ='C&F'!C60 -> 870.68 | I103: ='C&F'!D60 -> 565.65 | J103: ='C&F'!E60 -> 319.54 | K103: ='C&F'!F60 -> 1195.28 | L103: ='C&F'!G60 -> 959 | M103: =L45 -> 1668 | N103: =M45 -> 4261.1763 | O103: =N45 -> 6738.7737 | P103: =O45 -> 9501.8667 | Q103: =P45 -> 12431.225
D104: Closing Balance | F104: ₹ in MM | H104: ='C&F'!C61+Model!H102+Model!H103 -> 565.65 | I104: ='C&F'!D61+Model!I102+Model!I103 -> 319.54 | J104: ='C&F'!E61+Model!J102+Model!J103 -> 1195.28 | K104: ='C&F'!F61+Model!K102+Model!K103 -> 959.01 | L104: ='C&F'!G61+Model!L102+Model!L103 -> 1668 | M104: ='C&F'!H61+Model!M102+Model!M103 -> 4260.6963 | N104: ='C&F'!I61+Model!N102+Model!N103 -> 6738.3331 | O104: ='C&F'!J61+Model!O102+Model!O103 -> 9501.4667 | ... Q104: ='C&F'!L61+Model!Q102+Model!Q103 -> 15488.485
A108: Supporting Schedule
C110: Working Capital
D111: Account Recievable | F111: ₹ in MM | H111: ='C&F'!C24 -> -103.69 | I111: ='C&F'!D24 -> -1138.18 | J111: ='C&F'!E24 -> -789.75 | K111: ='C&F'!F24 -> -1642.3 | L111: ='C&F'!G24 -> -2115 | M111: =L47-M47 -> -81.949589 | N111: =M47-N47 -> -170.6932 | O111: =N47-O47 -> -66.445918 | P111: =O47-P47 -> -64.562648 | Q111: =P47-Q47 -> -83.545767
D112: Inventory | F112: ₹ in MM | H112: ='C&F'!C23 -> -622.09 | I112: ='C&F'!D23 -> -1380.05 | J112: ='C&F'!E23 -> -815.45 | K112: ='C&F'!F23 -> -1.89 | L112: ='C&F'!G23 -> -1432 | M112: =L48-M48 -> -429.51151 | N112: =M48-N48 -> -563.75478 | O112: =N48-O48 -> -511.77659 | P112: =O48-P48 -> -460.15369 | Q112: =P48-Q48 -> -410.34688
D113: Account Payable | F113: ₹ in MM | H113: ='C&F'!C29 -> 183.62 | I113: ='C&F'!D29 -> 349.05 | J113: ='C&F'!E29 -> 301.28 | K113: ='C&F'!F29 -> 319.6 | L113: ='C&F'!G29 -> 722 | M113: =M60-L60 -> 395.33145 | N113: =N60-M60 -> 326.96654 | O113: =O60-N60 -> 296.82022 | P113: =P60-O60 -> 266.87997 | Q113: =Q60-P60 -> 237.99301
D114: Others | F114: ₹ in MM | H114: =('C&F'!C26+'C&F'!C25+'C&F'!C27+'C&F'!C30+'C&F'!C31+'C&F'!C32) -> -330.77 | I114: =('C&F'!D26+'C&F'!D25+'C&F'!D27+'C&F'!D30+'C&F'!D31+'C&F'!D32) -> 546.72 | J114: =('C&F'!E26+'C&F'!E25+'C&F'!E27+'C&F'!E30+'C&F'!E31+'C&F'!E32) -> 374.27 | K114: =('C&F'!F26+'C&F'!F25+'C&F'!F27+'C&F'!F30+'C&F'!F31+'C&F'!F32) -> 288.4 | L114: =('C&F'!G26+'C&F'!G25+'C&F'!G27+'C&F'!G30+'C&F'!G31+'C&F'!G32) -> 1135 | M114: =L49-M49+M61-L61 -> 377.52 | N114: =M49-N49+N61-M61 -> 346.56336 | O114: =N49-O49+O61-N61 -> 314.61022 | P114: =O49-P49+P61-O61 -> 282.87549 | Q114: =P49-Q49+Q61-P61 -> 252.25718
D115: Total | F115: ₹ in MM | H115: =SUM(H111:H114) -> -872.93 | I115: =SUM(I111:I114) -> -1622.46 | J115: =SUM(J111:J114) -> -929.65 | K115: =SUM(K111:K114) -> -1036.19 | L115: =SUM(L111:L114) -> -1690 | M115: =SUM(M111:M114) -> 261.39035 | N115: =SUM(N111:N114) -> -60.918085 | O115: =SUM(O111:O114) -> 33.207932 | ... Q115: =SUM(Q111:Q114) -> -3.642451
C117: Depreciation
D118: PPE Opening | F118: ₹ in MM | I118: =H121 -> 3498.13 | J118: =I121 -> 3752.2 | K118: =J121 -> 4513.89 | L118: =K121 -> 4931.2 | M118: =L121 -> 5195 | N118: =M121 -> 4959.1636 | O118: =N121 -> 4717.4259 | P118: =O121 -> 4469.7104 | Q118: =P121 -> 4217.2765
D119: Plus Capex | F119: ₹ in MM | I119: =I121-I118-I120 -> 706.68 | J119: =J121-J118-J120 -> 1258.47 | K119: =K121-K118-K120 -> 960.55 | L119: =L121-L118-L120 -> 846.8 | M119: =(M25-L25)/M20 -> 414.00431 | N119: =(N25-M25)/N20 -> 378.60232 | O119: =(O25-N25)/O20 -> 342.38563 | P119: =(P25-O25)/P20 -> 306.68066 | Q119: =(Q25-P25)/Q20 -> 272.45154
D120: Less Depreciation | F120: ₹ in MM | H120: =-H81 -> -435.34 | I120: =-I81 -> -452.61 | J120: =-J81 -> -496.78 | K120: =-K81 -> -543.24 | L120: =-L81 -> -583 | M120: =-M118*M12 -> -649.84072 | N120: =-N118*N12 -> -620.34003 | O120: =-O118*O12 -> -590.10114 | P120: =-P118*P12 -> -559.11449 | Q120: =-Q118*Q12 -> -527.53764
D121: PPE Closing | F121: ₹ in MM | H121: =H52 -> 3498.13 | I121: =I52 -> 3752.2 | J121: =J52 -> 4513.89 | K121: =K52 -> 4931.2 | L121: =L52 -> 5195 | M121: =SUM(M118:M120) -> 4959.1636 | N121: =SUM(N118:N120) -> 4717.4259 | O121: =SUM(O118:O120) -> 4469.7104 | P121: =SUM(P118:P120) -> 4217.2765 | Q121: =SUM(Q118:Q120) -> 3962.1904
C123: Debt & Interest Schedule
...

Sheet DCF
A1: KSB LIMITED — DCF VALUATION MODEL (FCFF Method) | INR Millions
A2: Scenario-linked via dropdown (E5) → CHOOSE pulls from Scenario sheet | Yellow=Input | Base/Bull/Bear
A4: SCENARIO SELECTOR
A5: ► Select Scenario : | D5: Base Case | E5: =IF(D5="Base Case",1,IF(D5="Bull Case",2,3)) -> 1 | F5: =IF(D5="Base Case","Rev CAGR ~8% | Base ops",IF(D5="Bull Case","Rev CAGR ~23% | Nuclear ramp + peak cycle","Rev CAGR ~6.4% | Muted cycle")) -> Rev CAGR ~8% | Base ops
A6: Revenue Growth (Scenario-linked): | G6: =CHOOSE(E5,Scenario!F5,Scenario!F6,Scenario!F7) -> 0.08 | H6: =CHOOSE(E5,Scenario!G5,Scenario!G6,Scenario!G7) -> 0.068 | I6: =CHOOSE(E5,Scenario!H5,Scenario!H6,Scenario!H7) -> 0.0578 | J6: =CHOOSE(E5,Scenario!I5,Scenario!I6,Scenario!I7) -> 0.04913 | K6: =CHOOSE(E5,Scenario!J5,Scenario!J6,Scenario!J7) -> 0.0417605
A8: KEY ASSUMPTIONS
A9: Parameter | D9: Value | E9: Notes
A10: WACC | D10: 0.1163 | E10: From WACC sheet — Ke=12.18%, Kd=5.63%, We=99.75%
A11: Tax Rate | D11: 0.25 | E11: Effective rate consistent with FY2025 actuals
A12: EV/EBITDA Exit Multiple | D12: 15 | E12: Conservative vs peer median 25x | KSB trades 36x
A13: Terminal Growth Rate (g) | D13: 0.04 | E13: Long-term nominal GDP proxy = 4%
A14: Shares Outstanding (Crores) | D14: 17.4 | E14: FV ₹2 | Source: BSE
A15: Net Cash FY2025 (₹ MM) | D15: 18298 | E15: Cash+FDs 18,340 − Lease Liab 42 = 18,298
A16: Current Market Price (₹) | D16: 972 | E16: NSE price Apr 2026
A18: INCOME STATEMENT PROJECTIONS
A19: Line Item | C19: Units | D19: FY2025A | E19: FY2026E | F19: FY2027E | G19: FY2028E | H19: FY2029E | I19: FY2030E
A20: Revenue | C20: ₹ MM | D20: =Model!L25 -> 26957 | E20: =D20*(1+G6) -> 29113.56 | F20: =E20*(1+H6) -> 31093.282 | G20: =F20*(1+I6) -> 32890.474 | H20: =G20*(1+J6) -> 34506.383 | I20: =H20*(1+K6) -> 35947.387
A21: Revenue Growth % | C21: % | D21: — | E21: =E20/D20-1 -> 0.08 | F21: =F20/E20-1 -> 0.068 | G21: =G20/F20-1 -> 0.0578 | H21: =H20/G20-1 -> 0.04913 | I21: =I20/H20-1 -> 0.0417605
A22: COGS | C22: ₹ MM | D22: =Model!L26 -> -14563 | E22: =-E20*Model!L9 -> -15728.04 | F22: =-F20*Model!L9 -> -16797.547 | G22: =-G20*Model!L9 -> -17768.445 | H22: =-H20*Model!L9 -> -18641.409 | I22: =-I20*Model!L9 -> -19419.883
A23: Salaries | C23: ₹ MM | D23: =Model!L29 -> -3643 | E23: =-E20*Model!L10 -> -3934.44 | F23: =-F20*Model!L10 -> -4201.9819 | G23: =-G20*Model!L10 -> -4444.8565 | H23: =-H20*Model!L10 -> -4663.2323 | I23: =-I20*Model!L10 -> -4857.9712
A24: Other SG&A | C24: ₹ MM | D24: =Model!L30 -> -5016 | E24: =-E20*Model!L11 -> -5417.28 | F24: =-F20*Model!L11 -> -5785.655 | G24: =-G20*Model!L11 -> -6120.0659 | H24: =-H20*Model!L11 -> -6420.7447 | I24: =-I20*Model!L11 -> -6688.8782
A25: EBITDA | C25: ₹ MM | D25: =D20+D22+D23+D24 -> 3735 | E25: =D20+D22+D23+D24 -> 3735 | F25: =E20+E22+E23+E24 -> 4033.8 | G25: =F20+F22+F23+F24 -> 4308.0984 | H25: =G20+G22+G23+G24 -> 4557.1065 | I25: =H20+H22+H23+H24 -> 4780.9971
A26: EBITDA Margin | C26: % | D26: =D25/D20 -> 0.13855399 | E26: =E25/E20 -> 0.12829073 | F26: =F25/F20 -> 0.1297322 | G26: =G25/G20 -> 0.13098317 | H26: =H25/H20 -> 0.13206561 | I26: =I25/I20 -> 0.13299985
A27: D&A | C27: ₹ MM | D27: =Model!L32 -> -583 | E27: =-D20*Model!L12 -> -3187.0399 | F27: =-E20*Model!L12 -> -3442.0031 | G27: =-F20*Model!L12 -> -3676.0593 | H27: =-G20*Model!L12 -> -3888.5355 | I27: =-H20*Model!L12 -> -4079.5792
A28: EBIT | C28: ₹ MM | D28: =D25+D27 -> 3152 | E28: =D25+D27 -> 3152 | F28: =E25+E27 -> 547.96013 | G28: =F25+F27 -> 591.79694 | H28: =G25+G27 -> 632.03913 | I28: =H25+H27 -> 668.571
A29: EBIT Margin | C29: % | D29: =D28/D20 -> 0.11692696 | E29: =E28/E20 -> 0.1082657 | F29: =F28/F20 -> 0.017623104 | G29: =G28/G20 -> 0.017992959 | H29: =H28/H20 -> 0.018316586 | I29: =I28/I20 -> 0.018598598
A30: Interest | C30: ₹ MM | D30: =Model!L34 -> -30 | E30: =Model!L34 -> -30 | F30: =Model!M34 -> -2.94 | G30: =Model!N34 -> -2.94 | H30: =Model!O34 -> -2.94 | I30: =Model!P34 -> -2.94
A31: Other Income | C31: ₹ MM | D31: =Model!L35 -> 337 | E31: =E20*Model!L14 -> 363.96 | F31: =F20*Model!L14 -> 388.70928 | G31: =G20*Model!L14 -> 411.17668 | H31: =H20*Model!L14 -> 431.37779 | I31: =I20*Model!L14 -> 449.39234
A32: PBT | C32: ₹ MM | D32: =D28+D30+D31 -> 3459 | E32: =D28+D30+D31 -> 3459 | F32: =E28+E30+E31 -> 3485.96 | G32: =F28+F30+F31 -> 933.72941 | H32: =G28+G30+G31 -> 1000.0336 | I32: =H28+H30+H31 -> 1060.4769
A33: Tax | C33: ₹ MM | D33: =Model!L37 -> -900 | E33: =-E32*D11 -> -864.75 | F33: =-F32*D11 -> -871.49 | G33: =-G32*D11 -> -233.43235 | H33: =-H32*D11 -> -250.0084 | I33: =-I32*D11 -> -265.11923
A34: Net Earning | C34: ₹ MM | D34: =D32+D33 -> 2559 | E34: =D32+D33 -> 2559 | F34: =E32+E33 -> 2594.25 | G34: =F32+F33 -> 2614.47 | H34: =G32+G33 -> 700.29706 | I34: =H32+H33 -> 750.02521
A35: Net Margin | C35: % | D35: =D34/D20 -> 0.094928961 | E35: =E34/E20 -> 0.087897186 | F35: =F34/F20 -> 0.083434421 | G35: =G34/G20 -> 0.07949019 | H35: =H34/H20 -> 0.020294711 | I35: =I34/I20 -> 0.020864527
A36: EPS (FV ₹2) | C36: ₹ MM | D36: =D34/(D14*10) -> 14.706897 | E36: =D34/(D14*10) -> 14.706897 | F36: =E34/(D14*10) -> 14.706897 | G36: =F34/(D14*10) -> 14.909483 | H36: =G34/(D14*10) -> 15.02569 | I36: =H34/(D14*10) -> 4.0246957
A38: FREE CASH FLOW TO FIRM (FCFF)
A39: Line Item | C39: Units | D39: FY2026E | E39: FY2027E | F39: FY2028E | G39: FY2029E | H39: FY2030E
A40: EBIT | C40: ₹ MM | D40: =E28 -> 3152 | E40: =F28 -> 547.96013 | F40: =G28 -> 591.79694 | G40: =H28 -> 632.03913 | H40: =I28 -> 668.571 | I40: =H28 -> 632.03913
A41: Less: Cash Tax on EBIT | C41: ₹ MM | D41: =-D40*D11 -> -788 | E41: =-E40*D11 -> -136.99003 | F41: =-F40*D11 -> -147.94924 | G41: =-G40*D11 -> -158.00978 | H41: =-H40*D11 -> -167.14275 | I41: =-H40*D11 -> -167.14275
A42: NOPAT | C42: ₹ MM | D42: =D40+D41 -> 2364 | E42: =E40+E41 -> 410.9701 | F42: =F40+F41 -> 443.84771 | G42: =G40+G41 -> 474.02935 | H42: =H40+H41 -> 501.42825 | I42: =H40+H41 -> 501.42825
A43: Add: D&A | C43: ₹ MM | D43: =-E27 -> 3187.0399 | E43: =-F27 -> 3442.0031 | F43: =-G27 -> 3676.0593 | G43: =-H27 -> 3888.5355 | H43: =-I27 -> 4079.5792 | I43: =-H27 -> 3888.5355
A44: Less: Capex | C44: ₹ MM | D44: =Model!M121 -> 4959.1636 | E44: =Model!N121 -> 4717.4259 | F44: =Model!O121 -> 4469.7104 | G44: =Model!P121 -> 4217.2765 | H44: =Model!Q121 -> 3962.1904 | I44: =Model!Q121 -> 3962.1904
A45: Less: Change in NWC | C45: ₹ MM | D45: =Model!M152 -> 0 | E45: =Model!N152 -> 0 | F45: =Model!O152 -> 0 | G45: =Model!P152 -> 0 | H45: =Model!Q152 -> 0 | I45: =Model!Q152 -> 0
A46: FCFF | C46: ₹ MM | D46: =D42+D43+D44+D45 -> 10510.203 | E46: =E42+E43+E44+E45 -> 8570.399 | F46: =F42+F43+F44+F45 -> 8589.6173 | G46: =G42+G43+G44+G45 -> 8579.8414 | H46: =H42+H43+H44+H45 -> 8543.1979 | I46: =H42+H43+H44+H45 -> 8543.1979
A48: DCF — DISCOUNT & VALUATION
D49: FY2026E | E49: FY2027E | F49: FY2028E | G49: FY2029E | H49: FY2030E
A50: Discount Period (n) | D50: 1 | E50: 2 | F50: 3 | G50: 4 | H50: 5 | I50: 5
A51: Discount Factor = 1/(1+WACC)^n | D51: =1/(1+D10)^1 -> 0.89581654 | E51: =1/(1+D10)^2 -> 0.80248727 | F51: =1/(1+D10)^3 -> 0.71888136 | G51: =1/(1+D10)^4 -> 0.64398581 | H51: =1/(1+D10)^5 -> 0.57689314 | I51: =1/(1+D10)^5 -> 0.57689314
A52: PV of FCFF | D52: =D46*D51 -> 9415.2141 | E52: =E46*E51 -> 6877.6361 | F52: =F46*F51 -> 6174.9158 | G52: =G46*G51 -> 5525.2961 | H52: =H46*H51 -> 4928.5123 | I52: =H46*H51 -> 4928.5123
A53: Sum of PV of FCFFs | D53: =SUM(D52:H52) -> 32921.574 | E53: ← Sum of discounted FCFFs over 5-year forecast period
A55: TERMINAL VALUE CALCULATION | D55: TV (₹ MM) | E55: PV of TV | F55: TV % of EV | G55: Notes
A56: Gordon Growth (g=4%) | D56: =H46*(1+D13)/(D10-D13) -> 116447.26 | E56: =D56*H51 -> 67177.625 | F56: =E56/(D53+E56) -> 0.67111051 | G56: FCFF₂₀₃₀×(1+g)/(WACC−g)
A57: Exit Multiple (15x EBITDA) | D57: =I25*D12 -> 71714.957 | E57: =D57*H51 -> 41371.867 | F57: =E57/(D53+E57) -> 0.55687105 | G57: EBITDA₂₀₃₀ × 15x Exit Multiple
A59: ENTERPRISE VALUE → EQUITY VALUE → SHARE PRICE
D60: Gordon Growth | E60: Exit Multiple | F60: Average | G60: Notes
A61: Enterprise Value (EV) | D61: =D53+E56 -> 100099.2 | E61: =D53+E57 -> 74293.441 | F61: =AVERAGE(D61,E61) -> 87196.32 | G61: Sum PV FCFFs + PV Terminal Value
A62: Add: Net Cash (₹ MM) | D62: =D15 -> 18298 | E62: =D15 -> 18298 | F62: =D15 -> 18298 | G62: Cash+FDs 18,340 − Lease Liabilities 42 = 18,298
A63: Equity Value (₹ MM) | D63: =D61+D62 -> 118397.2 | E63: =E61+E62 -> 92591.441 | F63: =F61+F62 -> 105494.32 | G63: EV + Net Cash
A64: Shares Outstanding (MM) | D64: =D14*10 -> 174 | E64: =D14*10 -> 174 | F64: =D14*10 -> 174 | G64: 17.4 Crore × 10 = 174 MM shares
A65: Implied Share Price (₹) | D65: =D63/D64 -> 680.44367 | E65: =E63/E64 -> 532.13472 | F65: =F63/F64 -> 606.2892 | G65: Equity Value / Shares
A66: Current Market Price (₹) | D66: =D16 -> 972 | E66: =D16 -> 972 | F66: =D16 -> 972 | G66: NSE price Apr 2026
A67: Upside / (Downside) % | D67: =(D65-D66)/D66 -> -0.29995507 | E67: =(E65-D66)/D66 -> -0.4525363 | F67: =(F65-D66)/D66 -> -0.37624568 | G67: vs current market price
A69: SENSITIVITY — Implied Share Price (₹) | Gordon Growth | Base WACC=11.63%, g=4%
A70: WACC → | B70: 9.0% | C70: 10.0% | D70: 11.6% | E70: 12.0% | F70: 13.0% | G70: 14.0% | H70: g↕
A71: g = 2% | B71: =(E46/(1+0.09)^1+F46/(1+0.09)^2+G46/(1+0.09)^3+H46/(1+0.09)^4+I46/(1+0.09)^5+I46*(1+0.02)/(0.09-0.02)/(1+0.09)^5+D15)/(D14*10) -> 761.65591 | C71: =(E46/(1+0.1)^1+F46/(1+0.1)^2+G46/(1+0.1)^3+H46/(1+0.1)^4+I46/(1+0.1)^5+I46*(1+0.02)/(0.1-0.02)/(1+0.1)^5+D15)/(D14*10) -> 680.50804 | D71: =(E46/(1+0.1163)^1+F46/(1+0.1163)^2+G46/(1+0.1163)^3+H46/(1+0.1163)^4+I46/(1+0.1163)^5+I46*(1+0.02)/(0.1163-0.02)/(1+0.1163)^5+D15)/(D14*10) -> 584.30444 | E71: =(E46/(1+0.12)^1+F46/(1+0.12)^2+G46/(1+0.12)^3+H46/(1+0.12)^4+I46/(1+0.12)^5+I46*(1+0.02)/(0.12-0.02)/(1+0.12)^5+D15)/(D14*10) -> 566.82539 | F71: =(E46/(1+0.13)^1+F46/(1+0.13)^2+G46/(1+0.13)^3+H46/(1+0.13)^4+I46/(1+0.13)^5+I46*(1+0.02)/(0.13-0.02)/(1+0.13)^5+D15)/(D14*10) -> 525.45393 | G71: =(E46/(1+0.14)^1+F46/(1+0.14)^2+G46/(1+0.14)^3+H46/(1+0.14)^4+I46/(1+0.14)^5+I46*(1+0.02)/(0.14-0.02)/(1+0.14)^5+D15)/(D14*10) -> 490.95915 | H71: g=2%
A72: g = 3% | B72: =(E46/(1+0.09)^1+F46/(1+0.09)^2+G46/(1+0.09)^3+H46/(1+0.09)^4+I46/(1+0.09)^5+I46*(1+0.03)/(0.09-0.03)/(1+0.09)^5+D15)/(D14*10) -> 844.47224 | C72: =(E46/(1+0.1)^1+F46/(1+0.1)^2+G46/(1+0.1)^3+H46/(1+0.1)^4+I46/(1+0.1)^5+I46*(1+0.03)/(0.1-0.03)/(1+0.1)^5+D15)/(D14*10) -> 740.39227 | D72: =(E46/(1+0.1163)^1+F46/(1+0.1163)^2+G46/(1+0.1163)^3+H46/(1+0.1163)^4+I46/(1+0.1163)^5+I46*(1+0.03)/(0.1163-0.03)/(1+0.1163)^5+D15)/(D14*10) -> 622.35057 | E72: =(E46/(1+0.12)^1+F46/(1+0.12)^2+G46/(1+0.12)^3+H46/(1+0.12)^4+I46/(1+0.12)^5+I46*(1+0.03)/(0.12-0.03)/(1+0.12)^5+D15)/(D14*10) -> 601.49561 | F72: =(E46/(1+0.13)^1+F46/(1+0.13)^2+G46/(1+0.13)^3+H46/(1+0.13)^4+I46/(1+0.13)^5+I46*(1+0.03)/(0.13-0.03)/(1+0.13)^5+D15)/(D14*10) -> 552.8296 | G72: =(E46/(1+0.14)^1+F46/(1+0.14)^2+G46/(1+0.14)^3+H46/(1+0.14)^4+I46/(1+0.14)^5+I46*(1+0.03)/(0.14-0.03)/(1+0.14)^5+D15)/(D14*10) -> 512.98222 | H72: g=3%
A73: g = 4% | B73: =(E46/(1+0.09)^1+F46/(1+0.09)^2+G46/(1+0.09)^3+H46/(1+0.09)^4+I46/(1+0.09)^5+I46*(1+0.04)/(0.09-0.04)/(1+0.09)^5+D15)/(D14*10) -> 960.41509 | C73: =(E46/(1+0.1)^1+F46/(1+0.1)^2+G46/(1+0.1)^3+H46/(1+0.1)^4+I46/(1+0.1)^5+I46*(1+0.04)/(0.1-0.04)/(1+0.1)^5+D15)/(D14*10) -> 820.23791 | D73: =(E46/(1+0.1163)^1+F46/(1+0.1163)^2+G46/(1+0.1163)^3+H46/(1+0.1163)^4+I46/(1+0.1163)^5+I46*(1+0.04)/(0.1163-0.04)/(1+0.1163)^5+D15)/(D14*10) -> 670.36947 | E73: =(E46/(1+0.12)^1+F46/(1+0.12)^2+G46/(1+0.12)^3+H46/(1+0.12)^4+I46/(1+0.12)^5+I46*(1+0.04)/(0.12-0.04)/(1+0.12)^5+D15)/(D14*10) -> 644.83339 | F73: =(E46/(1+0.13)^1+F46/(1+0.13)^2+G46/(1+0.13)^3+H46/(1+0.13)^4+I46/(1+0.13)^5+I46*(1+0.04)/(0.13-0.04)/(1+0.13)^5+D15)/(D14*10) -> 586.28875 | G73: =(E46/(1+0.14)^1+F46/(1+0.14)^2+G46/(1+0.14)^3+H46/(1+0.14)^4+I46/(1+0.14)^5+I46*(1+0.04)/(0.14-0.04)/(1+0.14)^5+D15)/(D14*10) -> 539.4099 | H73: g=4%
A74: g = 5% | B74: =(E46/(1+0.09)^1+F46/(1+0.09)^2+G46/(1+0.09)^3+H46/(1+0.09)^4+I46/(1+0.09)^5+I46*(1+0.05)/(0.09-0.05)/(1+0.09)^5+D15)/(D14*10) -> 1134.3294 | C74: =(E46/(1+0.1)^1+F46/(1+0.1)^2+G46/(1+0.1)^3+H46/(1+0.1)^4+I46/(1+0.1)^5+I46*(1+0.05)/(0.1-0.05)/(1+0.1)^5+D15)/(D14*10) -> 932.0218 | D74: =(E46/(1+0.1163)^1+F46/(1+0.1163)^2+G46/(1+0.1163)^3+H46/(1+0.1163)^4+I46/(1+0.1163)^5+I46*(1+0.05)/(0.1163-0.05)/(1+0.1163)^5+D15)/(D14*10) -> 732.8737 | E74: =(E46/(1+0.12)^1+F46/(1+0.12)^2+G46/(1+0.12)^3+H46/(1+0.12)^4+I46/(1+0.12)^5+I46*(1+0.05)/(0.12-0.05)/(1+0.12)^5+D15)/(D14*10) -> 700.55339 | F74: =(E46/(1+0.13)^1+F46/(1+0.13)^2+G46/(1+0.13)^3+H46/(1+0.13)^4+I46/(1+0.13)^5+I46*(1+0.05)/(0.13-0.05)/(1+0.13)^5+D15)/(D14*10) -> 628.1127 | G74: =(E46/(1+0.14)^1+F46/(1+0.14)^2+G46/(1+0.14)^3+H46/(1+0.14)^4+I46/(1+0.14)^5+I46*(1+0.05)/(0.14-0.05)/(1+0.14)^5+D15)/(D14*10) -> 571.71041 | H74: g=5%
A75: g = 6% | B75: =(E46/(1+0.09)^1+F46/(1+0.09)^2+G46/(1+0.09)^3+H46/(1+0.09)^4+I46/(1+0.09)^5+I46*(1+0.06)/(0.09-0.06)/(1+0.09)^5+D15)/(D14*10) -> 1424.1865 | C75: =(E46/(1+0.1)^1+F46/(1+0.1)^2+G46/(1+0.1)^3+H46/(1+0.1)^4+I46/(1+0.1)^5+I46*(1+0.06)/(0.1-0.06)/(1+0.1)^5+D15)/(D14*10) -> 1099.6976 | D75: =(E46/(1+0.1163)^1+F46/(1+0.1163)^2+G46/(1+0.1163)^3+H46/(1+0.1163)^4+I46/(1+0.1163)^5+I46*(1+0.06)/(0.1163-0.06)/(1+0.1163)^5+D15)/(D14*10) -> 817.58193 | E75: =(E46/(1+0.12)^1+F46/(1+0.12)^2+G46/(1+0.12)^3+H46/(1+0.12)^4+I46/(1+0.12)^5+I46*(1+0.06)/(0.12-0.06)/(1+0.12)^5+D15)/(D14*10) -> 774.84672 | F75: =(E46/(1+0.13)^1+F46/(1+0.13)^2+G46/(1+0.13)^3+H46/(1+0.13)^4+I46/(1+0.13)^5+I46*(1+0.06)/(0.13-0.06)/(1+0.13)^5+D15)/(D14*10) -> 681.88633 | G75: =(E46/(1+0.14)^1+F46/(1+0.14)^2+G46/(1+0.14)^3+H46/(1+0.14)^4+I46/(1+0.14)^5+I46*(1+0.06)/(0.14-0.06)/(1+0.14)^5+D15)/(D14*10) -> 612.08604 | H75: g=6%

Sheet Comp Valuation
A1: KSB LTD
A2: Comp Valuation
E4: Market Data | M4: Financial Data | Q4: Valuation
E5: Ticker | F5: Price | G5: Shares | H5: Market Cap | I5: Debt | J5: Cash | K5: EV | M5: Sales | N5: EBITDA | O5: Earning | Q5: Ev/Sale | R5: Ev/EBITDA | S5: P/E
D6: Company | F6: (₹/Share) | G6: M | H6: ₹ MM | I6: ₹ MM | J6: ₹ MM | K6: ₹ MM | M6: ₹ MM | N6: ₹ MM | O6: ₹ MM | Q6: x | R6: x | S6: x
D8: Kirloskar Brothers Ltd | E8: KIRLOSBROS | F8: 1775 | G8: 58 | H8: =F8*G8 -> 102950 | I8: 2850 | J8: 8200 | K8: =H8+I8-J8 -> 97600 | M8: 44922 | N8: 5100 | O8: 4151 | Q8: =K8/M8 -> 2.1726548 | R8: =K8/N8 -> 19.137255 | S8: =H8/O8 -> 24.801253
D9: Elgi Equipments Ltd | E9: ELGIEQUIP | F9: 580 | G9: 315 | H9: =F9*G9 -> 182700 | I9: 1200 | J9: 12500 | K9: =H9+I9-J9 -> 171400 | M9: 35105 | N9: 5827 | O9: 3447 | Q9: =K9/M9 -> 4.8824954 | R9: =K9/N9 -> 29.414793 | S9: =H9/O9 -> 53.002611
D10: Cummins India Ltd | E10: CUMMINSI | F10: 2510 | G10: 277 | H10: =F10*G10 -> 695270 | I10: 2100 | J10: 28000 | K10: =H10+I10-J10 -> 669370 | M10: 89520 | N10: 16800 | O10: 12500 | Q10: =K10/M10 -> 7.4773235 | R10: =K10/N10 -> 39.843452 | S10: =H10/O10 -> 55.6216
D11: Triveni Turbine Ltd | E11: TRITURBINE | F11: 620 | G11: 330 | H11: =F11*G11 -> 204600 | I11: 800 | J11: 6500 | K11: =H11+I11-J11 -> 198900 | M11: 20400 | N11: 4200 | O11: 3420 | Q11: =K11/M11 -> 9.75 | R11: =K11/N11 -> 47.357143 | S11: =H11/O11 -> 59.824561
D12: Ingersoll Rand India | E12: INGERRAN | F12: 3800 | G12: 29 | H12: =F12*G12 -> 110200 | I12: 0 | J12: 8500 | K12: =H12+I12-J12 -> 101700 | M12: 13250 | N12: 3100 | O12: 2350 | Q12: =K12/M12 -> 7.6754717 | R12: =K12/N12 -> 32.806452 | S12: =H12/O12 -> 46.893617
D13: Shakti Pumps India Ltd | E13: SHAKTIPU | F13: 1050 | G13: 27 | H13: =F13*G13 -> 28350 | I13: 3200 | J13: 2800 | K13: =H13+I13-J13 -> 28750 | M13: 9840 | N13: 1950 | O13: 1420 | Q13: =K13/M13 -> 2.921748 | R13: =K13/N13 -> 14.74359 | S13: =H13/O13 -> 19.964789
D14: WPIL Ltd | E14: WPIL | F14: 570 | G14: 14 | H14: =F14*G14 -> 7980 | I14: 1800 | J14: 1200 | K14: =H14+I14-J14 -> 8580 | M14: 5830 | N14: 870 | O14: 620 | Q14: =K14/M14 -> 1.4716981 | R14: =K14/N14 -> 9.862069 | S14: =H14/O14 -> 12.870968
D15: Roto Pumps Ltd | E15: ROTOPUMP | F15: 460 | G15: 14 | H15: =F15*G15 -> 6440 | I15: 350 | J15: 950 | K15: =H15+I15-J15 -> 5840 | M15: 2850 | N15: 510 | O15: 350 | Q15: =K15/M15 -> 2.0491228 | R15: =K15/N15 -> 11.45098 | S15: =H15/O15 -> 18.4
D16: Isgec Heavy Engineering | E16: ISGEC | F16: 1050 | G16: 36 | H16: =F16*G16 -> 37800 | I16: 15000 | J16: 8500 | K16: =H16+I16-J16 -> 44300 | M16: 37500 | N16: 4500 | O16: 3100 | Q16: =K16/M16 -> 1.1813333 | R16: =K16/N16 -> 9.8444444 | S16: =H16/O16 -> 12.193548
D17: Grindwell Norton Ltd | E17: GRINDWEL | F17: 1820 | G17: 78 | H17: =F17*G17 -> 141960 | I17: 0 | J17: 11500 | K17: =H17+I17-J17 -> 130460 | M17: 24000 | N17: 5100 | O17: 3950 | Q17: =K17/M17 -> 5.4358333 | R17: =K17/N17 -> 25.580392 | S17: =H17/O17 -> 35.939241
D19: Average | Q19: =AVERAGE(Q8:Q17) -> 4.5017681 | R19: =AVERAGE(R8:R17) -> 24.004057 | S19: =AVERAGE(S8:S17) -> 33.951219
D20: Median | Q20: =MEDIAN(Q8:Q17) -> 3.9021217 | R20: =MEDIAN(R8:R17) -> 22.358824 | S20: =MEDIAN(S8:S17) -> 30.370247
D22: KSB Limited | E22: KSB | F22: 972 | G22: 174 | H22: 16912.8 | I22: 42 | J22: 18340 | K22: -1385.2 | M22: 26957 | N22: 3714 | O22: 2559 | Q22: =IF(K22>0,H22/K22,"N/M") -> N/M | R22: =IF(AND(N22>0,K22>0),K22/N22,"N/M") -> N/M | S22: =IF(O22>0,H22/O22,"N/M") -> 6.6091442
D24: Metric | E24: Comp | F24: Key Metric | G24: EV | H24: Net Debt (Debt−Cash) | I24: Equity Value (EV−Debt+Cash) | J24: Share | K24: Share Price
E25: X | G25: MM | H25: MM | I25: MM | J25: Crs
D27: EV/Revenue | E27: 4.746985 | F27: =M22 -> 26957 | G27: =F27*E27 -> 127964.47 | H27: -18298 | I27: 146262 | J27: =G22 -> 174 | K27: =I27/J27 -> 840.58621
D28: EV/EBITDA | E28: 25.308727 | F28: =N22 -> 3714 | G28: =E28*F28 -> 93996.611 | H28: -18298 | I28: 112295 | J28: =G22 -> 174 | K28: =I28/J28 -> 645.37356
D29: P/E | E29: 35.703225 | F29: =O22 -> 2559 | G29: =I29+-H29 -> 109655 | H29: -18298 | I29: 91357 | J29: =J28 -> 174 | K29: =I29/J29 -> 525.04023
D30: Current Market Price | K30: 972

Sheet WACC
A1: KSB LTD
A2: Weighted-Average Cost of Capital (WACC)
A4: Comparable Companies Beta
D7: Company | E7: Ticker | H7: Equity Value | I7: Total Debt | J7: Debt/Equity | K7: Debt/Capital | L7: Tax Rate | M7: Levered Beta | N7: Unlevered Beta
D9: Kirloskar Brothers Ltd | E9: KIRLOSBROS | H9: ='Comp Valuation'!H8 -> 102950 | I9: ='Comp Valuation'!I8 -> 2850 | J9: =I9/H9 -> 0.027683341 | K9: =I9/(H9+I9) -> 0.026937618 | L9: 0.275 | M9: 0.85 | N9: =M9/(1+J9*(1-L9)) -> 0.8332758
D10: Elgi Equipments Ltd | E10: ELGIEQUIP | H10: ='Comp Valuation'!H9 -> 182700 | I10: ='Comp Valuation'!I9 -> 1200 | J10: =I10/H10 -> 0.0065681445 | K10: =I10/(H10+I10) -> 0.0065252855 | L10: 0.262 | M10: 0.8 | N10: =M10/(1+J10*(1-L10)) -> 0.79614087
D11: Cummins India Ltd | E11: CUMMINSIND | H11: ='Comp Valuation'!H10 -> 695270 | I11: ='Comp Valuation'!I10 -> 2100 | J11: =I11/H11 -> 0.0030204093 | K11: =I11/(H11+I11) -> 0.0030113139 | L11: 0.248 | M11: 0.75 | N11: =M11/(1+J11*(1-L11)) -> 0.74830035
D12: Triveni Turbine Ltd | E12: TRITURBINE | H12: ='Comp Valuation'!H11 -> 204600 | I12: ='Comp Valuation'!I11 -> 800 | J12: =I12/H12 -> 0.0039100684 | K12: =I12/(H12+I12) -> 0.0038948393 | L12: 0.253 | M12: 0.9 | N12: =M12/(1+J12*(1-L12)) -> 0.89737892
D13: Ingersoll Rand India | E13: INGERRAND | H13: ='Comp Valuation'!H12 -> 110200 | I13: ='Comp Valuation'!I12 -> 0 | J13: =I13/H13 -> 0 | K13: =I13/(H13+I13) -> 0 | L13: 0.256 | M13: 0.7 | N13: =M13/(1+J13*(1-L13)) -> 0.7
D14: Shakti Pumps India Ltd | E14: SHAKTIPUMP | H14: ='Comp Valuation'!H13 -> 28350 | I14: ='Comp Valuation'!I13 -> 3200 | J14: =I14/H14 -> 0.11287478 | K14: =I14/(H14+I14) -> 0.10142631 | L14: 0.245 | M14: 1.1 | N14: =M14/(1+J14*(1-L14)) -> 1.0136189
D15: WPIL Ltd | E15: WPIL | H15: ='Comp Valuation'!H14 -> 7980 | I15: ='Comp Valuation'!I14 -> 1800 | J15: =I15/H15 -> 0.22556391 | K15: =I15/(H15+I15) -> 0.18404908 | L15: 0.281 | M15: 0.95 | N15: =M15/(1+J15*(1-L15)) -> 0.817429
D16: Roto Pumps Ltd | E16: ROTOPUMPS | H16: ='Comp Valuation'!H15 -> 6440 | I16: ='Comp Valuation'!I15 -> 350 | J16: =I16/H16 -> 0.054347826 | K16: =I16/(H16+I16) -> 0.051546392 | L16: 0.269 | M16: 0.85 | N16: =M16/(1+J16*(1-L16)) -> 0.8175213
D17: Isgec Heavy Engineering | E17: ISGEC | H17: ='Comp Valuation'!H16 -> 37800 | I17: ='Comp Valuation'!I16 -> 15000 | J17: =I17/H17 -> 0.3968254 | K17: =I17/(H17+I17) -> 0.28409091 | L17: 0.292 | M17: 1.05 | N17: =M17/(1+J17*(1-L17)) -> 0.8197026
D18: Grindwell Norton Ltd | E18: GRINDWELL | H18: ='Comp Valuation'!H17 -> 141960 | I18: ='Comp Valuation'!I17 -> 0 | J18: =I18/H18 -> 0 | K18: =I18/(H18+I18) -> 0 | L18: 0.247 | M18: 0.75 | N18: =M18/(1+J18*(1-L18)) -> 0.75
D20: Average | J20: =AVERAGE(J9:J18) -> 0.083079388 | K20: =AVERAGE(K9:K18) -> 0.066148174 | L20: =AVERAGE(L9:L18) -> 0.2628 | M20: =AVERAGE(M9:M18) -> 0.87 | N20: =AVERAGE(N9:N18) -> 0.81933678
D21: Median | J21: =MEDIAN(J9:J18) -> 0.017125743 | K21: =MEDIAN(K9:K18) -> 0.016731452 | L21: =MEDIAN(L9:L18) -> 0.259 | M21: =MEDIAN(M9:M18) -> 0.85 | N21: =MEDIAN(N9:N18) -> 0.81747515
D23: KSB Limited | E23: KSB | F23: Source: NSE/BSE | H23: 16913 | I23: 42 | J23: =I23/H23 -> 0.0024832969 | K23: 0.029828486 | L23: 0.25 | M23: 0.83748848
D25: WACC Calculation
D27: Total Capital Structure
D29: Proportion of debt | E29: =J20 -> 0.083079388
D30: Proportion of Equity | E30: =1-E29 -> 0.91692061
D31: Current Capital Structure
D32: Market Cap | E32: =H23 -> 16913
D33: Total Debt | E33: =I23 -> 42 | F33: ← Lease Liabilities only per Annual Report (no bank borrowings). Screener shows 520 incorrectly.
D34: Debt/Equity | E34: =J23 -> 0.0024832969
D36: Cost Of Debt
D37: Pre-tax Cost of Debt | E37: 0.075
D38: Tax Rate | E38: =L23 -> 0.25
D39: After-Tax Cost of Debt | E39: =E37*(1-E38) -> 0.05625
D41: Cost Of Equity
D42: Risk Free Rate | E42: 0.071
D43: Equity Market Return | E43: 0.133
D44: Equity Risk Premium | E44: =E43-E42 -> 0.062
D45: Levered Equity Beta | E45: =N21*(1+E34*(1-E38)) -> 0.81899767
D46: Cost of Equity | E46: =E42+(E44*E45) -> 0.12177786
D48: WACC | E48: =E29*E39+E46*E30 -> 0.11633384

Sheet Beta
A1: KSB Limited
A2: Company Beta — 5 Year Monthly Returns (Apr 2021 – Apr 2026)
A4: Month | B4: Index Close Price (Nifty 50) | C4: % Change Monthly | D4: Stock Close Price (KSB) | E4: % Change Monthly
A5: Apr-21 | B5: 14631.1 | D5: 1123
A6: May-21 | B6: 15582.8 | C6: =B6/B5-1 -> 0.065046374 | D6: 1187 | E6: =D6/D5-1 -> 0.056990205 | G6: Max | H6: =MAX(D53:D65) -> 4445
A7: Jun-21 | B7: 15721.5 | C7: =B7/B6-1 -> 0.0089008394 | D7: 1298 | E7: =D7/D6-1 -> 0.093513058 | G7: Min | H7: =MIN(D53:D65) -> 3867
A8: Jul-21 | B8: 16118.2 | C8: =B8/B7-1 -> 0.025232961 | D8: 1455 | E8: =D8/D7-1 -> 0.12095532
A9: Aug-21 | B9: 17132.2 | C9: =B9/B8-1 -> 0.062910251 | D9: 1568 | E9: =D9/D8-1 -> 0.07766323
A10: Sep-21 | B10: 17618.15 | C10: =B10/B9-1 -> 0.028364717 | D10: 1735 | E10: =D10/D9-1 -> 0.1065051 | G10: Beta | H10: =SLOPE(E6:E65,C6:C65) -> 1.4909927
A11: Oct-21 | B11: 18477.05 | C11: =B11/B10-1 -> 0.048750862 | D11: 1890 | E11: =D11/D10-1 -> 0.089337176
A12: Nov-21 | B12: 17026.45 | C12: =B12/B11-1 -> -0.078508203 | D12: 1812 | E12: =D12/D11-1 -> -0.041269841
A13: Dec-21 | B13: 17354.05 | C13: =B13/B12-1 -> 0.019240652 | D13: 1956 | E13: =D13/D12-1 -> 0.079470199
A14: Jan-22 | B14: 17339.85 | C14: =B14/B13-1 -> -0.0008182528 | D14: 2043 | E14: =D14/D13-1 -> 0.044478528
A15: Feb-22 | B15: 16793.9 | C15: =B15/B14-1 -> -0.031485278 | D15: 1987 | E15: =D15/D14-1 -> -0.027410671
A16: Mar-22 | B16: 17464.75 | C16: =B16/B15-1 -> 0.039946052 | D16: 2089 | E16: =D16/D15-1 -> 0.051333669
A17: Apr-22 | B17: 17102.55 | C17: =B17/B16-1 -> -0.020738917 | D17: 1980 | E17: =D17/D16-1 -> -0.052178076
A18: May-22 | B18: 16584.3 | C18: =B18/B17-1 -> -0.030302499 | D18: 1845 | E18: =D18/D17-1 -> -0.068181818
A19: Jun-22 | B19: 15780.25 | C19: =B19/B18-1 -> -0.048482601 | D19: 1678 | E19: =D19/D18-1 -> -0.090514905
A20: Jul-22 | B20: 17158.25 | C20: =B20/B19-1 -> 0.087324345 | D20: 1923 | E20: =D20/D19-1 -> 0.14600715
A21: Aug-22 | B21: 17759.3 | C21: =B21/B20-1 -> 0.035029796 | D21: 2105 | E21: =D21/D20-1 -> 0.094643786
A22: Sep-22 | B22: 17094.35 | C22: =B22/B21-1 -> -0.037442354 | D22: 2012 | E22: =D22/D21-1 -> -0.044180523
... A65: Apr-26 | B65: 24955.5 | C65: =B65/B64-1 -> 0.014876147 | D65: 4156 | E65: =D65/D64-1 -> 0.016385424

Sheet Summary
A1: KSB LTD
A2: Valuation Summary — Football Field
A4: Football Field Data
K5: Market
H6: Comp | I6: DCF | J6: 52-week hi/Lo | K6: Consenses
D7: High | H7: =MAX('Comp Valuation'!K27:K29) -> 840.58621 | I7: 746.89767 | J7: =Beta!H6/10 -> 444.5 | K7: 972
D8: High | H8: =H7 -> 840.58621 | I8: =I7 -> 746.89767 | J8: =J7 -> 444.5 | K8: 972
D9: Low | H9: =MIN('Comp Valuation'!K27:K29) -> 525.04023 | I9: 594.11576 | J9: =Beta!H7/10 -> 386.7 | K9: 716
D10: Low | H10: =H9 -> 525.04023 | I10: =I9 -> 594.11576 | J10: =J9 -> 386.7 | K10: 716
A12: Valuation Summary Chart
